Workbook

Sheet Aidez-moi
A1: Classeur d'atelier — module M03 (Excel pour l'analyse de données)
A3: Généré le 2026-09-18 par tools/classeur_M03.py. Ne pas modifier à la main : toute valeur de contrôle provient de 01_socle_donnees/data/reference/chiffres_cites.md.
A5: Feuilles et à quoi elles servent :
A6: ventes_brutes — le fichier REÇU par l'entreprise : 489 lignes × 13 colonnes, tout en texte, défauts compris (montants avec séparateur, dates manuscrites, doublons).
A7: ventes — le fichier NETTOYÉ (l'attendu du projet M01) : 480 lignes, types corrigés, montants en nombres. C'est la feuille de travail du module.
A8: produits · clients · magasins · vendeurs · objectifs — les référentiels, pour les recherches (RECHERCHEX, INDEX/EQUIV) et le rapprochement des objectifs.
A9: Calculs — une ligne par fonction de la fiche : le nom affiché, la formule telle qu'elle est stockée, la valeur attendue, la valeur rendue, et une colonne de contrôle.
A10: TCD — le tableau croisé que votre TCD doit reproduire, construit au COUNTIFS/SUMIFS. Si votre TCD ne rend pas ces nombres, l'un des deux a tort.
A11: Mensuel — le chiffre d'affaires mois par mois et l'objectif correspondant, avec le doute à lire avant toute conclusion de performance.
A13: Trois choses à vérifier avant de toucher à une formule :
A14: 1. la barre de formule montre ce que la cellule CONTIENT ; l'affichage montre ce qu'elle MONTRE ;
A15: 2. 486 montants sur 489 de la feuille ventes_brutes sont du texte : un =SOMME() y renvoie 0, et ce n'est pas une erreur du tableur ;
... A18: En cas d'écart avec le manuel : relancer `python3 01_socle_donnees/scripts/chiffres_manuel.py M01 M02 M03` puis `python3 tools/classeur_M03.py`.

Sheet ventes_brutes
A1: n_ticket | B1: date | C1: heure | D1: magasin | E1: vendeur | F1: client | G1: produit | H1: categorie | I1: quantite | J1: prix_unitaire_ht | K1: remise | L1: montant_ht | M1: montant_ttc
A2: T05-250101-075845 | B2: 2025-01-01 | C2: 11:01 | D2: Magasin 5 — Kaya Marché | E2: Moussa Ilboudo | F2: 10857 | G2: Plâtre de construction 25 kg — réf 1 | H2: Matériaux | I2: 11 | J2: 4500 | K2: 0.03 | L2: 48015 | M2: 56 658
A3: T05-250101-075846 | B3: 2025-01-01 | C3: 09:32 | D3: Magasin 5 — Kaya Marché | E3: Salamatu Sankara | F3: 0 | G3: Gravier 15/25 (m3) — réf 2 | H3: Matériaux | I3: 2000 | J3: 21950 | K3: 0.0 | L3: 43900 | M3: 51 802
A4: T05-250101-075847 | B4: 2025-01-01 | C4: 07:51 | D4: Magasin 5 — Kaya Marché | E4: Salamatu Sankara | F4: 17552 | G4: Sable de rivière (m3) — réf 1 | H4: Matériaux | I4: 2 | J4: 25775 | K4: 0.04 | L4: 49488 | M4: 58 396
A5: T05-250101-075848 | B5: 2025-01-01 | C5: 15:17 | D5: Magasin 5 — Kaya Marché | E5: Adama Bationo | F5: 2150 | G5: Échelle aluminium 4 marches — réf 1 | H5: Consommables | I5: 6 | J5: 8275 | K5: 0.0 | L5: 49650 | M5: 58 587
A6: T05-250101-075849 | B6: 2025-01-01 | C6: 10:33 | D6: Magasin 5 — Kaya Marché | E6: Adama Bationo | F6: 0 | G6: Sable de rivière (m3) — réf 1 | H6: Matériaux | I6: 3 | J6: 26325 | K6: 0.0 | L6: 78975 | M6: 93 191
A7: T05-250101-075850 | B7: 2025-01-01 | C7: 18:08 | D7: Magasin 5 — Kaya Marché | E7: Moussa Ilboudo | F7: 0 | G7: Ciment CPJ45 50 kg — réf 2 | H7: Matériaux | I7: 12 | J7: 6550 | K7: 0.0 | L7: 78600 | M7: 92 748
A8: T05-250101-075851 | B8: 2025-01-01 | C8: 13:22 | D8: Magasin 5 — Kaya Marché | E8: Adama Bationo | F8: 10176 | G8: Hourdis creux 12 — réf 1 | H8: Matériaux | I8: 6 | J8: 1025 | K8: 0.0 | L8: 6150 | M8: 7 257
A9: T05-250101-075852 | B9: 2025-01-01 | C9: 08:17 | D9: Magasin 5 — Kaya Marché | E9: Boureima Ouédraogo | F9: 11417 | G9: Meuleuse 125 mm — réf 2 | H9: Quincaillerie | I9: 9 | J9: 5850 | K9: 0.0 | L9: 52650 | M9: 62 127
A10: T05-250101-075853 | B10: 01/01/2025 | C10: 16:15 | D10: Magasin 5 — Kaya Marché | E10: Salamatu Sankara | F10: 1519 | G10: Fil de fer recuit (kg) — réf 2 | H10: Quincaillerie | I10: 3 | J10: 2000 | K10: 0.04 | L10: 5760 | M10: 6 797
A11: T05-250101-075854 | B11: 2025-01-01 | C11: 08:21 | D11: Magasin 5 — Kaya Marché | E11: Salamatu Sankara | F11: 6969 | G11: Casque de chantier — réf 1 | H11: Consommables | I11: 2 | J11: 8300 | K11: 0.0 | L11: 16600 | M11: 19 588
A12: T05-250101-075855 | B12: 2025-01-01 | C12: 15:35 | D12: Magasin 5 — Kaya Marché | E12: Boureima Ouédraogo | F12: 17857 | G12: Sac de transport 100 kg — réf 1 | H12: Consommables | I12: 2 | J12: 8525 | K12: 0.07 | L12: 15856 | M12: 18 710
... A20: T05-250101-075863 | B20: 01/01/2025 | C20: 08:54 | D20: Magasin 5 — Kaya Marché | E20: Adama Bationo | F20: 20824 | G20: Régulateur de charge 10 A — réf 2 | H20: Electricité | I20: 4 | J20: 11625 | K20: 0.0 | L20: 46500 | M20: 54 870
A21: T05-250101-075864 | B21: 2025-01-01 | C21: 16:58 | D21: Magasin 5 — Kaya Marché | E21: Salamatu Sankara | G21: Colle à carrelage 25 kg — réf 2 | H21: Matériaux | I21: 14 | J21: 4450 | K21: 0.0 | L21: 62300 | M21: 73 514
A22: T05-250101-075865 | B22: 01/01/2025 | C22: 08:16 | D22: Magasin 5 — Kaya Marché | E22: Adama Bationo | G22: Ballon d'eau chaude 50 L — réf 1 | H22: Plomberie | I22: 2 | J22: 34025 | K22: 0.0 | L22: 68050 | M22: 80 299
A23: T05-250102-075995 | B23: 2025-01-02 | C23: 16:16 | D23: Magasin 5 — Kaya Marché | E23: Boureima Ouédraogo | F23: 20631 | G23: Sable de rivière (m3) — réf 2 | H23: Matériaux | I23: 4 | J23: 27050 | K23: 0.0 | L23: 108200 | M23: 127 676
A24: T05-250102-075996 | B24: 2025-01-02 | C24: 11:23 | D24: Magasin 5 — Kaya Marché | E24: Boureima Ouédraogo | F24: 0 | G24: Brique de terre cuite — réf 2 | H24: Matériaux | I24: 7 | J24: 700 | K24: 0.0 | L24: 4900 | M24: 5 782
A25: T05-250102-075997 | B25: 2025-01-02 | C25: 09:31 | D25: Magasin 5 — Kaya Marché | E25: Boureima Ouédraogo | F25: 16066 | G25: Ciment CPJ45 50 kg — réf 1 | H25: Matériaux | I25: 12 | J25: 6100 | K25: 0.0 | L25: 73200 | M25: 86 376
A26: T05-250102-075998 | B26: 2025-01-02 | C26: 08:17 | D26: Magasin 5 — Kaya Marché | E26: Adama Bationo | F26: 17124 | G26: Hourdis creux 12 — réf 1 | H26: Matériaux | I26: 6 | J26: 1075 | K26: 0.08 | L26: 5934 | M26: 7 002
A27: T05-250102-075999 | B27: 2025-01-02 | C27: 17:27 | D27: Magasin 5 — Kaya Marché | E27: Adama Bationo | F27: 8234 | G27: Casque de chantier — réf 2 | H27: Consommables | I27: 27 | J27: 5400 | K27: 0.0 | L27: 145800 | M27: 172 044
A28: T05-250102-076000 | B28: 2025-01-02 | C28: 08:18 | D28: Magasin 5 — Kaya Marché | E28: Boureima Ouédraogo | F28: 5812 | G28: Tableau 18 modules — réf 1 | H28: Electricité | I28: 25 | J28: 8700 | K28: 0.08 | L28: 200100 | M28: 236 118
A29: T05-250102-076001 | B29: 2025-01-02 | C29: 07:43 | D29: Magasin 5 — Kaya Marché | E29: Moussa Ilboudo | F29: 9745 | G29: Pavé autobloquant — réf 2 | H29: Matériaux | I29: 3 | J29: 675 | K29: 0.0 | L29: 2025 | M29: 2 389
A30: T05-250102-076002 | B30: 02/01/2025 | C30: 10:32 | D30: Magasin 5 — Kaya Marché | E30: Salamatu Sankara | F30: 21264 | G30: Mètre ruban 5 m — réf 1 | H30: Quincaillerie | I30: 12 | J30: 7475 | K30: 0.04 | L30: 86112 | M30: 101 612
A31: T05-250102-076003 | B31: 2025-01-02 | C31: 10:37 | D31: Magasin 5 — Kaya Marché | E31: Boureima Ouédraogo | F31: 20263 | G31: Ciment CPJ45 50 kg — réf 1 | H31: Matériaux | I31: 1 | J31: 6100 | K31: 0.0 | L31: 6100 | M31: 7 198
A32: T05-250102-076004 | B32: 2025-01-02 | C32: 07:12 | D32: Magasin 5 — Kaya Marché | E32: Salamatu Sankara | G32: Tube PVC évacuation 100 mm (ml) — réf 1 | H32: Plomberie | I32: 5000 | J32: 3500 | K32: 0.0 | L32: 17500 | M32: 20 650
A33: T05-250102-076005 | B33: 2025-01-02 | C33: 08:40 | D33: Magasin 5 — Kaya Marché | E33: Boureima Ouédraogo | F33: 16610 | G33: Peinture glycéro 1 L — réf 2 | H33: Peinture | I33: 17 | J33: 3925 | K33: 0.0 | L33: 66725 | M33: 78 735
A34: T05-250102-076006 | B34: 02/01/2025 | C34: 12:58 | D34: Magasin 5 — Kaya Marché | E34: Boureima Ouédraogo | G34: Colle à carrelage 25 kg — réf 2 | H34: Matériaux | I34: 5 | J34: 4300 | K34: 0.04 | L34: 20640 | M34: 24 355
A35: T05-250102-076007 | B35: 2025-01-02 | C35: 18:53 | D35: Magasin 5 — Kaya Marché | E35: Adama Bationo | F35: 2691 | G35: Raccord laiton 20/27 — réf 2 | H35: Plomberie | I35: 4 | J35: 4825 | K35: 0.04 | L35: 18528 | M35: 21 863
A36: T05-250102-076008 | B36: 2025-01-02 | C36: 14:52 | D36: Magasin 5 — Kaya Marché | E36: Salamatu Sankara | F36: 16233 | G36: Pelle carrée — réf 2 | H36: Consommables | I36: 2 | J36: 5100 | K36: 0.0 | L36: 10200 | M36: 12 036
A37: T05-250102-076009 | B37: 2025-01-02 | C37: 16:14 | D37: Magasin 5 — Kaya Marché | E37: Boureima Ouédraogo | F37: 2178 | G37: Sac de transport 100 kg — réf 1 | H37: Consommables | I37: 2 | J37: 8775 | K37: 0.04 | L37: 16848 | M37: 19 881
A38: T05-250102-076010 | B38: 2025-01-02 | C38: 12:34 | D38: Magasin 5 — Kaya Marché | E38: Salamatu Sankara | F38: 12170 | G38: Brique de terre cuite — réf 2 | H38: Matériaux | I38: 2 | J38: 675 | K38: 0.0 | L38: 1350 | M38: 1 593
A39: T05-250102-076011 | B39: 02/01/2025 | C39: 18:01 | D39: Magasin 5 — Kaya Marché | E39: Moussa Ilboudo | F39: 2474 | G39: Tout-venant (m3) — réf 1 | H39: Matériaux | I39: 4 | J39: 16375 | K39: 0.04 | L39: 62880 | M39: 74 198
A40: T05-250102-076012 | B40: 2025-01-02 | C40: 13:31 | D40: Magasin 5 — Kaya Marché | E40: Adama Bationo | F40: 4653 | G40: Parpaing 15 aggloméré — réf 2 | H40: Matériaux | I40: 5 | J40: 1400 | K40: 0.0 | L40: 7000 | M40: 8 260
A41: T05-250102-076013 | B41: 2025-01-02 | C41: 12:57 | D41: Magasin 5 — Kaya Marché | E41: Salamatu Sankara | F41: 7529 | G41: Régulateur de charge 10 A — réf 1 | H41: Electricité | I41: 3 | J41: 21675 | K41: 0.03 | L41: 63074 | M41: 74 427
A42: T05-250201-079456 | B42: 2025-02-01 | C42: 13:52 | D42: Magasin 5 — Kaya Marché | E42: Boureima Ouédraogo | F42: 3742 | G42: Té fonte 100 — réf 1 | H42: Plomberie | I42: 1 | J42: 3150 | K42: 0.04 | L42: 3024 | M42: 3 568
A43: T05-250201-079457 | B43: 2025-02-01 | C43: 09:27 | D43: Magasin 5 — Kaya Marché | E43: Moussa Ilboudo | F43: 0 | G43: Peinture glycéro 1 L — réf 1 | H43: Peinture | I43: 21 | J43: 3300 | K43: 0.0 | L43: 69300 | M43: 81 774
A44: T05-250201-079458 | B44: 2025-02-01 | C44: 18:28 | D44: Magasin 5 — Kaya Marché | E44: Salamatu Sankara | F44: 21909 | G44: Carreau de pavement 40x40 — réf 1 | H44: Matériaux | I44: 4 | J44: 1025 | K44: 0.0 | L44: 4100 | M44: 4 838
A45: T05-250201-079459 | B45: 2025-02-01 | C45: 16:55 | D45: Magasin 5 — Kaya Marché | E45: Moussa Ilboudo | F45: 21680 | G45: Lampe solaire murale — réf 1 | H45: Electricité | I45: 5 | J45: 10525 | K45: 0.03 | L45: 51046 | M45: 60 234
A46: T05-250201-079460 | B46: 2025-02-01 | C46: 18:22 | D46: Magasin 5 — Kaya Marché | E46: Salamatu Sankara | F46: 1519 | G46: Colle à carrelage 25 kg — réf 1 | H46: Matériaux | I46: 8 | J46: 6100 | K46: 0.04 | L46: 46848 | M46: 55 281
... A74: T05-250203-079681 | B74: 2025-02-03 | C74: 07:33 | D74: Magasin 5 — Kaya Marché | E74: Salamatu Sankara | F74: 23278 | G74: Antirouille rouge brique 1 L — réf 2 | H74: Peinture | I74: 3 | J74: 6800 | K74: 0.03 | L74: 19788 | M74: 23 350
A75: T05-250203-079682 | B75: 2025-02-03 | C75: 16:45 | D75: Magasin 5 — Kaya Marché | E75: Moussa Ilboudo | G75: Gants anti-coupure (paire) — réf 1 | H75: Consommables | I75: 6 | J75: 8925 | K75: 0.0 | L75: 53550 | M75: 63 189
A76: T05-250203-079683 | B76: 2025-02-03 | C76: 10:30 | D76: Magasin 5 — Kaya Marché | E76: Salamatu Sankara | F76: 9467 | G76: Clé plate 13 — réf 1 | H76: Quincaillerie | I76: 3 | J76: 9725 | K76: 0.0 | L76: 29175 | M76: 34 427
A77: T05-250203-079684 | B77: 2025-02-03 | C77: 11:32 | D77: Magasin 5 — Kaya Marché | E77: Salamatu Sankara | F77: 11926 | G77: Brique de terre cuite — réf 1 | H77: Matériaux | I77: 4 | J77: 1050 | K77: 0.04 | L77: 4032 | M77: 4 758
A78: T05-250203-079684 | B78: 2025-02-03 | C78: 11:32 | D78: Magasin 5 — Kaya Marché | E78: Salamatu Sankara | F78: 11926 | G78: Brique de terre cuite — réf 1 | H78: Matériaux | I78: 4 | J78: 1050 | K78: 0.04 | L78: 4032 | M78: 4 758
A79: T05-250203-079685 | B79: 2025-02-03 | C79: 15:11 | D79: Magasin 5 — Kaya Marché | E79: Salamatu Sankara | F79: 756 | G79: Carreau de pavement 40x40 — réf 1 | H79: Matériaux | I79: 5 | J79: 1075 | K79: 0.0 | L79: 5375 | M79: 6 343
A80: T05-250203-079686 | B80: 2025-02-03 | C80: 14:03 | D80: Magasin 5 — Kaya Marché | E80: Moussa Ilboudo | F80: 5532 | G80: Vernis marin 1 L — réf 1 | H80: Peinture | I80: 6000 | J80: 5800 | K80: 0.0 | L80: 34800 | M80: 41 064
A81: T05-250203-079687 | B81: 2025-02-03 | C81: 18:08 | D81: Magasin 5 — Kaya Marché | E81: Adama Bationo | F81: 22119 | G81: Bêche à manche bois — réf 1 | H81: Consommables | I81: 4 | J81: 5175 | K81: 0.0 | L81: 20700 | M81: 24 426
A82: T05-250203-079688 | B82: 2025-02-03 | C82: 17:18 | D82: Magasin 5 — Kaya Marché | E82: Adama Bationo | F82: 10043 | G82: Gravier 15/25 (m3) — réf 1 | H82: Matériaux | I82: 2 | J82: 31200 | K82: 0.08 | L82: 57408 | M82: 67 741
A83: T05-250203-079689 | B83: 03/02/2025 | C83: 09:39 | D83: Magasin 5 — Kaya Marché | E83: Boureima Ouédraogo | F83: 14715 | G83: Robinet mitigeur évier — réf 2 | H83: Plomberie | I83: 5 | J83: 36200 | K83: 0.04 | L83: 173760 | M83: 205 037
A84: T05-250301-082692 | B84: 2025-03-01 | C84: 13:52 | D84: Magasin 5 — Kaya Marché | E84: Moussa Ilboudo | F84: 19875 | G84: Tournevis cruciforme PH2 — réf 1 | H84: Quincaillerie | I84: 3 | J84: 8200 | K84: 0.04 | L84: 23616 | M84: 27 867
A85: T05-250301-082693 | B85: 2025-03-01 | C85: 18:17 | D85: Magasin 5 — Kaya Marché | E85: Salamatu Sankara | F85: 12170 | G85: Diluant nitro 5 L — réf 2 | H85: Peinture | I85: 27 | J85: 4375 | K85: 0.0 | L85: 118125 | M85: 139 387
A86: T05-250301-082694 | B86: 2025-03-01 | C86: 15:12 | D86: Magasin 5 — Kaya Marché | E86: Salamatu Sankara | F86: 19501 | G86: Parpaing 15 aggloméré — réf 1 | H86: Matériaux | I86: 2 | J86: 1500 | K86: 0.04 | L86: 2880 | M86: 3 398
A87: T05-250301-082695 | B87: 2025-03-01 | C87: 12:20 | D87: Magasin 5 — Kaya Marché | E87: Moussa Ilboudo | F87: 5578 | G87: Pavé autobloquant — réf 2 | H87: Matériaux | I87: 2 | J87: 675 | K87: 0.03 | L87: 1310 | M87: 1 546
... A113: T05-250302-082744 | B113: 2025-03-02 | C113: 08:47 | D113: Magasin 5 — Kaya Marché | E113: Boureima Ouédraogo | F113: 3668 | G113: Marteau de menuisier — réf 2 | H113: Quincaillerie | I113: 4 | J113: 8725 | K113: 0.0 | L113: 34900 | M113: 41 182
A114: T05-250302-082745 | B114: 2025-03-02 | C114: 11:13 | D114: Magasin 5 — Kaya Marché | E114: Adama Bationo | G114: Tout-venant (m3) — réf 1 | H114: Matériaux | I114: 9 | J114: 16475 | K114: 0.0 | L114: 148275 | M114: 174 965
A115: T05-250302-082745 | B115: 2025-03-02 | C115: 11:52 | D115: Magasin 5 — Kaya Marché | E115: Adama Bationo | F115: 19185 | G115: Lampe solaire murale — réf 1 | H115: Electricité | I115: 3 | J115: 10175 | K115: 0.0 | L115: 30525 | M115: 36 019
A116: T05-250303-082910 | B116: 2025-03-03 | C116: 08:03 | D116: Magasin 5 — Kaya Marché | E116: Moussa Ilboudo | F116: 0 | G116: Marteau de menuisier — réf 2 | H116: Quincaillerie | I116: 1 | J116: 8775 | K116: 0.0 | L116: 8775 | M116: 10 355
A117: T05-250303-082910 | B117: 2025-03-03 | C117: 16:39 | D117: Magasin 5 — Kaya Marché | E117: Salamatu Sankara | F117: 4415 | G117: Tableau 18 modules — réf 2 | H117: Electricité | I117: 1 | J117: 9075 | K117: 0.0 | L117: 9075 | M117: 10 709
A118: T05-250303-082911 | B118: 2025-03-03 | C118: 07:06 | D118: Magasin 5 — Kaya Marché | E118: Salamatu Sankara | F118: 13669 | G118: Brouette 90 L — réf 2 | H118: Consommables | I118: 1 | J118: 9875 | K118: 0.0 | L118: 9875 | M118: 11 653
A119: T05-250303-082911 | B119: 2025-03-03 | C119: 09:44 | D119: Magasin 5 — Kaya Marché | E119: Salamatu Sankara | F119: 5228 | G119: Marteau de menuisier — réf 1 | H119: Quincaillerie | I119: 8 | J119: 9400 | K119: 0.08 | L119: 69184 | M119: 81 637
A120: T05-250303-082912 | B120: 2025-03-03 | C120: 08:38 | D120: Magasin 5 — Kaya Marché | E120: Salamatu Sankara | F120: 16351 | G120: Panneau solaire 100 W — réf 2 | H120: Electricité | I120: 1 | J120: 15575 | K120: 0.03 | L120: 15108 | M120: 17 827
A121: T05-250303-082912 | B121: 2025-03-03 | C121: 08:47 | D121: Magasin 5 — Kaya Marché | E121: Salamatu Sankara | F121: 9672 | G121: Tournevis cruciforme PH2 — réf 1 | H121: Quincaillerie | I121: 13 | J121: 7900 | K121: 0.04 | L121: 98592 | M121: 116 339
A122: T05-250303-082913 | B122: 2025-03-03 | C122: 16:01 | D122: Magasin 5 — Kaya Marché | E122: Adama Bationo | F122: 22643 | G122: Robinet mitigeur évier — réf 1 | H122: Plomberie | I122: 26 | J122: 33375 | K122: 0.04 | L122: 833040 | M122: 982 987
A123: T05-250303-082913 | B123: 2025-03-03 | C123: 16:03 | D123: Magasin 5 — Kaya Marché | E123: Salamatu Sankara | F123: 640 | G123: Pavé autobloquant — réf 2 | H123: Matériaux | I123: 2 | J123: 700 | K123: 0.0 | L123: 1400 | M123: 1 652
A124: T05-250401-086352 | B124: 01/04/2025 | C124: 11:01 | D124: Magasin 5 — Kaya Marché | E124: Boureima Ouédraogo | F124: 0 | G124: Échelle aluminium 4 marches — réf 1 | H124: Consommables | I124: 3 | J124: 8650 | K124: 0.0 | L124: 25950 | M124: 30 621
A125: T05-250401-086353 | B125: 2025-04-01 | C125: 12:45 | D125: Magasin 5 — Kaya Marché | E125: Moussa Ilboudo | F125: 13771 | G125: Plaque de plâtre 13 mm — réf 2 | H125: Bois & panneaux | I125: 4 | J125: 13900 | K125: 0.04 | L125: 53376 | M125: 62 984
A126: T05-250401-086353 | B126: 2025-04-01 | C126: 12:45 | D126: Magasin 5 — Kaya Marché | E126: Moussa Ilboudo | F126: 13771 | G126: Plaque de plâtre 13 mm — réf 2 | H126: Bois & panneaux | I126: 4 | J126: 13900 | K126: 0.04 | L126: 53376 | M126: 62 984
... A130: T05-250401-086357 | B130: 2025-04-01 | C130: 13:18 | D130: Magasin 5 — Kaya Marché | E130: Adama Bationo | F130: 22824 | G130: Chasse d'eau 6 L — réf 1 | H130: Plomberie | I130: -5 | J130: 26625 | K130: 0.04 | L130: -127800 | M130: -150 804
A131: T05-250401-086358 | B131: 2025-04-01 | C131: 17:48 | D131: Magasin 5 — Kaya Marché | E131: Boureima Ouédraogo | G131: Tube PER 16x2 (rouleau) — réf 2 | H131: Plomberie | I131: 3 | J131: 3300 | K131: 0.0 | L131: 9900 | M131: 11 682
A132: T05-250401-086359 | B132: 01/04/2025 | C132: 18:04 | D132: Magasin 5 — Kaya Marché | E132: Adama Bationo | F132: 0 | G132: Tube PVC évacuation 100 mm (ml) — réf 1 | H132: Plomberie | I132: 2 | J132: 3475 | K132: 0.0 | L132: 6950 | M132: 8 201
A133: T05-250401-086360 | B133: 2025-04-01 | C133: 08:47 | D133: Magasin 5 — Kaya Marché | E133: Salamatu Sankara | F133: 20670 | G133: Enduit de rebouchage 5 kg — réf 1 | H133: Peinture | I133: 11 | J133: 4225 | K133: 0.0 | L133: 46475 | M133: 54 841
A134: T05-250401-086361 | B134: 2025-04-01 | C134: 10:42 | D134: Magasin 5 — Kaya Marché | E134: Adama Bationo | G134: Coude PVC 90° 100 — réf 1 | H134: Plomberie | I134: 3 | J134: 4075 | K134: 0.0 | L134: 12225 | M134: 14 425
A135: T05-250401-086362 | B135: 2025-04-01 | C135: 16:34 | D135: Magasin 5 — Kaya Marché | E135: Boureima Ouédraogo | F135: 2446 | G135: Peinture glycéro 1 L — réf 1 | H135: Peinture | I135: 12 | J135: 3250 | K135: 0.0 | L135: 39000 | M135: 46 020
A136: T05-250401-086363 | B136: 2025-04-01 | C136: 15:34 | D136: Magasin 5 — Kaya Marché | E136: Moussa Ilboudo | F136: 12082 | G136: Sac de transport 100 kg — réf 1 | H136: Consommables | I136: 2 | J136: 8650 | K136: 0.04 | L136: 16608 | M136: 19 597
A137: T05-250401-086364 | B137: 2025-04-01 | C137: 11:16 | D137: Magasin 5 — Kaya Marché | E137: Salamatu Sankara | F137: 367 | G137: Hourdis creux 12 — réf 2 | H137: Matériaux | I137: 4 | J137: 1500 | K137: 0.04 | L137: 5760 | M137: 6 797
A138: T05-250401-086365 | B138: 2025-04-01 | C138: 15:20 | D138: Magasin 5 — Kaya Marché | E138: Adama Bationo | F138: 0 | G138: Gravier 15/25 (m3) — réf 1 | H138: Matériaux | I138: 5000 | J138: 30550 | K138: 0.0 | L138: 152750 | M138: 180 245
A139: T05-250401-086366 | B139: 2025-04-01 | C139: 10:34 | D139: Magasin 5 — Kaya Marché | E139: Adama Bationo | F139: 2661 | G139: Douche de toilettes — réf 2 | H139: Plomberie | I139: 13 | J139: 30850 | K139: 0.0 | L139: 401050 | M139: 473 239
A140: T05-250401-086367 | B140: 2025-04-01 | C140: 12:11 | D140: Magasin 5 — Kaya Marché | E140: Boureima Ouédraogo | F140: 12489 | G140: Pavé autobloquant — réf 1 | H140: Matériaux | I140: 1000 | J140: 1125 | K140: 0.0 | L140: 1125 | M140: 1 327
A141: T05-250401-086368 | B141: 2025-04-01 | C141: 10:06 | D141: Magasin 5 — Kaya Marché | E141: Boureima Ouédraogo | F141: 9106 | G141: Tout-venant (m3) — réf 2 | H141: Matériaux | I141: 5 | J141: 23400 | K141: 0.0 | L141: 117000 | M141: 138 060
A142: T05-250401-086369 | B142: 2025-04-01 | C142: 12:57 | D142: Magasin 5 — Kaya Marché | E142: Boureima Ouédraogo | F142: 21755 | G142: Perforateur 800 W — réf 1 | H142: Quincaillerie | I142: 2 | J142: 8000 | K142: 0.08 | L142: 14720 | M142: 17 370
A143: T05-250401-086370 | B143: 2025-04-01 | C143: 13:30 | D143: Magasin 5 — Kaya Marché | E143: Moussa Ilboudo | F143: 0 | G143: Perforateur 800 W — réf 2 | H143: Quincaillerie | I143: 2 | J143: 5800 | K143: 0.0 | L143: 11600 | M143: 13 688
A144: T05-250401-086371 | B144: 2025-04-01 | C144: 17:32 | D144: Magasin 5 — Kaya Marché | E144: Adama Bationo | F144: 3959 | G144: Passe-câble étanche — réf 1 | H144: Electricité | I144: 2 | J144: 16775 | K144: 0.0 | L144: 33550 | M144: 39 589
A145: T05-250401-086372 | B145: 2025-04-01 | C145: 16:07 | D145: Magasin 5 — Kaya Marché | E145: Adama Bationo | F145: 18885 | G145: Sable de rivière (m3) — réf 1 | H145: Matériaux | I145: 4 | J145: 25975 | K145: 0.0 | L145: 103900 | M145: 122 602
A146: T05-250401-086373 | B146: 2025-04-01 | C146: 17:07 | D146: Magasin 5 — Kaya Marché | E146: Adama Bationo | F146: 22027 | G146: Cheville nylon 8 mm (sachet) — réf 2 | H146: Quincaillerie | I146: 11 | J146: 2175 | K146: 0.04 | L146: 22968 | M146: 27 102
A147: T05-250401-086374 | B147: 2025-04-01 | C147: 11:48 | D147: Magasin 5 — Kaya Marché | E147: Salamatu Sankara | G147: Cheville nylon 8 mm (sachet) — réf 2 | H147: Quincaillerie | I147: 5 | J147: 2150 | K147: 0.0 | L147: 10750 | M147: 12 685
A148: T05-250401-086375 | B148: 2025-04-01 | C148: 15:23 | D148: Magasin 5 — Kaya Marché | E148: Moussa Ilboudo | F148: 5345 | G148: Pince coupante 200 mm — réf 1 | H148: Quincaillerie | I148: -3 | J148: 5200 | K148: 0.0 | L148: -15600 | M148: -18 408
A149: T05-250401-086376 | B149: 01/04/2025 | C149: 16:39 | D149: Magasin 5 — Kaya Marché | E149: Moussa Ilboudo | F149: 19650 | G149: Bêche à manche bois — réf 2 | H149: Consommables | I149: -3 | J149: 5800 | K149: 0.04 | L149: -16704 | M149: -19 711
A150: T05-250401-086377 | B150: 2025-04-01 | C150: 11:37 | D150: Magasin 5 — Kaya Marché | E150: Adama Bationo | F150: 23136 | G150: Tableau 18 modules — réf 1 | H150: Electricité | I150: 3 | J150: 8775 | K150: 0.04 | L150: 25272 | M150: 29 821
A151: T05-250401-086378 | B151: 2025-04-01 | C151: 16:36 | D151: Magasin 5 — Kaya Marché | E151: Adama Bationo | F151: 15288 | G151: Scie égoïne 500 mm — réf 1 | H151: Quincaillerie | I151: 4 | J151: 10975 | K151: 0.0 | L151: 43900 | M151: 51 802
A152: T05-250401-086379 | B152: 2025-04-01 | C152: 16:47 | D152: Magasin 5 — Kaya Marché | E152: Salamatu Sankara | F152: 9940 | G152: Hourdis creux 12 — réf 2 | H152: Matériaux | I152: 4 | J152: 1550 | K152: 0.0 | L152: 6200 | M152: 7 316
A153: T05-250401-086380 | B153: 2025-04-01 | C153: 17:13 | D153: Magasin 5 — Kaya Marché | E153: Salamatu Sankara | F153: 11981 | G153: Tournevis cruciforme PH2 — réf 1 | H153: Quincaillerie | I153: 10 | J153: 8200 | K153: 0.0 | L153: 82000 | M153: 96 760
A154: T05-250402-086501 | B154: 2025-04-02 | C154: 08:43 | D154: Magasin 5 — Kaya Marché | E154: Adama Bationo | F154: 19457 | G154: Brouette 90 L — réf 2 | H154: Consommables | I154: 7 | J154: 10125 | K154: 0.03 | L154: 68749 | M154: 81 124
A155: T05-250402-086501 | B155: 02/04/2025 | C155: 10:29 | D155: Magasin 5 — Kaya Marché | E155: Salamatu Sankara | F155: 7706 | G155: Peinture glycéro 1 L — réf 2 | H155: Peinture | I155: 16 | J155: 3900 | K155: 0.04 | L155: 59904 | M155: 70 687
A156: T05-250402-086502 | B156: 2025-04-02 | C156: 17:58 | D156: Magasin 5 — Kaya Marché | E156: Salamatu Sankara | F156: 8920 | G156: Chasse d'eau 6 L — réf 1 | H156: Plomberie | I156: 3 | J156: 25900 | K156: 0.04 | L156: 74592 | M156: 88 019
A157: T05-250402-086502 | B157: 2025-04-02 | C157: 08:11 | D157: Magasin 5 — Kaya Marché | E157: Adama Bationo | F157: 6563 | G157: Écrou hexagonal 10 (sachet) — réf 1 | H157: Quincaillerie | I157: -4 | J157: 1450 | K157: 0.04 | L157: -5568 | M157: -6 570
A158: T05-250402-086503 | B158: 2025-04-02 | C158: 18:21 | D158: Magasin 5 — Kaya Marché | E158: Salamatu Sankara | F158: 2883 | G158: Gravier 15/25 (m3) — réf 1 | H158: Matériaux | I158: 4 | J158: 30950 | K158: 0.08 | L158: 113896 | M158: 134 397
A159: T05-250402-086503 | B159: 02/04/2025 | C159: 18:23 | D159: Magasin 5 — Kaya Marché | E159: Salamatu Sankara | F159: 14971 | G159: Ciment CPJ45 50 kg — réf 2 | H159: Matériaux | I159: 17 | J159: 6475 | K159: 0.04 | L159: 105672 | M159: 124 693
... A175: T05-250501-090472 | B175: 2025-05-01 | C175: 15:40 | D175: Magasin 5 — Kaya Marché | E175: Boureima Ouédraogo | F175: 14106 | G175: Pince coupante 200 mm — réf 2 | H175: Quincaillerie | I175: 2 | J175: 10500 | K175: 0.04 | L175: 20160 | M175: 23 789
A176: T05-250501-090472 | B176: 01/05/2025 | C176: 09:38 | D176: Magasin 5 — Kaya Marché | E176: Adama Bationo | G176: Chasse d'eau 6 L — réf 1 | H176: Plomberie | I176: 3 | J176: 26075 | K176: 0.0 | L176: 78225 | M176: 92 305
A177: T05-250501-090472 | B177: 2025-05-01 | C177: 15:17 | D177: Magasin 5 — Kaya Marché | E177: Adama Bationo | F177: 10827 | G177: Enduit de rebouchage 5 kg — réf 1 | H177: Peinture | I177: 9 | J177: 4250 | K177: 0.0 | L177: 38250 | M177: 45 135
...

Sheet ventes
A1: n_ticket | B1: date | C1: heure | D1: magasin | E1: vendeur | F1: client | G1: produit | H1: categorie | I1: quantite | J1: prix_unitaire_ht | K1: remise | L1: montant_ht | M1: montant_ttc | N1: montant recalculé (colonne utilitaire)
A2: T05-250101-075845 | B2: 45658 | C2: 11:01 | D2: Magasin 5 — Kaya Marché | E2: Moussa Ilboudo | F2: 10857 | G2: Plâtre de construction 25 kg — réf 1 | H2: Matériaux | I2: 11 | J2: 4500 | K2: 0.03 | L2: 48015 | M2: 56658 | N2: =ROUND(I2*J2*(1-K2),0)
A3: T05-250101-075846 | B3: 45658 | C3: 09:32 | D3: Magasin 5 — Kaya Marché | E3: Salamatu Sankara | F3: 0 | G3: Gravier 15/25 (m3) — réf 2 | H3: Matériaux | I3: 2 | J3: 21950 | K3: 0 | L3: 43900 | M3: 51802 | N3: =ROUND(I3*J3*(1-K3),0)
A4: T05-250101-075847 | B4: 45658 | C4: 07:51 | D4: Magasin 5 — Kaya Marché | E4: Salamatu Sankara | F4: 17552 | G4: Sable de rivière (m3) — réf 1 | H4: Matériaux | I4: 2 | J4: 25775 | K4: 0.04 | L4: 49488 | M4: 58396 | N4: =ROUND(I4*J4*(1-K4),0)
A5: T05-250101-075848 | B5: 45658 | C5: 15:17 | D5: Magasin 5 — Kaya Marché | E5: Adama Bationo | F5: 2150 | G5: Échelle aluminium 4 marches — réf 1 | H5: Consommables | I5: 6 | J5: 8275 | K5: 0 | L5: 49650 | M5: 58587 | N5: =ROUND(I5*J5*(1-K5),0)
A6: T05-250101-075849 | B6: 45658 | C6: 10:33 | D6: Magasin 5 — Kaya Marché | E6: Adama Bationo | F6: 0 | G6: Sable de rivière (m3) — réf 1 | H6: Matériaux | I6: 3 | J6: 26325 | K6: 0 | L6: 78975 | M6: 93191 | N6: =ROUND(I6*J6*(1-K6),0)
A7: T05-250101-075850 | B7: 45658 | C7: 18:08 | D7: Magasin 5 — Kaya Marché | E7: Moussa Ilboudo | F7: 0 | G7: Ciment CPJ45 50 kg — réf 2 | H7: Matériaux | I7: 12 | J7: 6550 | K7: 0 | L7: 78600 | M7: 92748 | N7: =ROUND(I7*J7*(1-K7),0)
A8: T05-250101-075851 | B8: 45658 | C8: 13:22 | D8: Magasin 5 — Kaya Marché | E8: Adama Bationo | F8: 10176 | G8: Hourdis creux 12 — réf 1 | H8: Matériaux | I8: 6 | J8: 1025 | K8: 0 | L8: 6150 | M8: 7257 | N8: =ROUND(I8*J8*(1-K8),0)
A9: T05-250101-075852 | B9: 45658 | C9: 08:17 | D9: Magasin 5 — Kaya Marché | E9: Boureima Ouédraogo | F9: 11417 | G9: Meuleuse 125 mm — réf 2 | H9: Quincaillerie | I9: 9 | J9: 5850 | K9: 0 | L9: 52650 | M9: 62127 | N9: =ROUND(I9*J9*(1-K9),0)
A10: T05-250101-075853 | B10: 45658 | C10: 16:15 | D10: Magasin 5 — Kaya Marché | E10: Salamatu Sankara | F10: 1519 | G10: Fil de fer recuit (kg) — réf 2 | H10: Quincaillerie | I10: 3 | J10: 2000 | K10: 0.04 | L10: 5760 | M10: 6797 | N10: =ROUND(I10*J10*(1-K10),0)
A11: T05-250101-075854 | B11: 45658 | C11: 08:21 | D11: Magasin 5 — Kaya Marché | E11: Salamatu Sankara | F11: 6969 | G11: Casque de chantier — réf 1 | H11: Consommables | I11: 2 | J11: 8300 | K11: 0 | L11: 16600 | M11: 19588 | N11: =ROUND(I11*J11*(1-K11),0)
A12: T05-250101-075855 | B12: 45658 | C12: 15:35 | D12: Magasin 5 — Kaya Marché | E12: Boureima Ouédraogo | F12: 17857 | G12: Sac de transport 100 kg — réf 1 | H12: Consommables | I12: 2 | J12: 8525 | K12: 0.07 | L12: 15856 | M12: 18710 | N12: =ROUND(I12*J12*(1-K12),0)
A13: T05-250101-075856 | B13: 45658 | C13: 07:27 | D13: Magasin 5 — Kaya Marché | E13: Boureima Ouédraogo | F13: 17861 | G13: Hourdis creux 12 — réf 1 | H13: Matériaux | I13: 8 | J13: 1075 | K13: 0 | L13: 8600 | M13: 10148 | N13: =ROUND(I13*J13*(1-K13),0)
... A20: T05-250101-075863 | B20: 45658 | C20: 08:54 | D20: Magasin 5 — Kaya Marché | E20: Adama Bationo | F20: 20824 | G20: Régulateur de charge 10 A — réf 2 | H20: Electricité | I20: 4 | J20: 11625 | K20: 0 | L20: 46500 | M20: 54870 | N20: =ROUND(I20*J20*(1-K20),0)
A21: T05-250101-075864 | B21: 45658 | C21: 16:58 | D21: Magasin 5 — Kaya Marché | E21: Salamatu Sankara | G21: Colle à carrelage 25 kg — réf 2 | H21: Matériaux | I21: 14 | J21: 4450 | K21: 0 | L21: 62300 | M21: 73514 | N21: =ROUND(I21*J21*(1-K21),0)
A22: T05-250101-075865 | B22: 45658 | C22: 08:16 | D22: Magasin 5 — Kaya Marché | E22: Adama Bationo | G22: Ballon d'eau chaude 50 L — réf 1 | H22: Plomberie | I22: 2 | J22: 34025 | K22: 0 | L22: 68050 | M22: 80299 | N22: =ROUND(I22*J22*(1-K22),0)
A23: T05-250102-075995 | B23: 45659 | C23: 16:16 | D23: Magasin 5 — Kaya Marché | E23: Boureima Ouédraogo | F23: 20631 | G23: Sable de rivière (m3) — réf 2 | H23: Matériaux | I23: 4 | J23: 27050 | K23: 0 | L23: 108200 | M23: 127676 | N23: =ROUND(I23*J23*(1-K23),0)
A24: T05-250102-075996 | B24: 45659 | C24: 11:23 | D24: Magasin 5 — Kaya Marché | E24: Boureima Ouédraogo | F24: 0 | G24: Brique de terre cuite — réf 2 | H24: Matériaux | I24: 7 | J24: 700 | K24: 0 | L24: 4900 | M24: 5782 | N24: =ROUND(I24*J24*(1-K24),0)
A25: T05-250102-075997 | B25: 45659 | C25: 09:31 | D25: Magasin 5 — Kaya Marché | E25: Boureima Ouédraogo | F25: 16066 | G25: Ciment CPJ45 50 kg — réf 1 | H25: Matériaux | I25: 12 | J25: 6100 | K25: 0 | L25: 73200 | M25: 86376 | N25: =ROUND(I25*J25*(1-K25),0)
A26: T05-250102-075998 | B26: 45659 | C26: 08:17 | D26: Magasin 5 — Kaya Marché | E26: Adama Bationo | F26: 17124 | G26: Hourdis creux 12 — réf 1 | H26: Matériaux | I26: 6 | J26: 1075 | K26: 0.08 | L26: 5934 | M26: 7002 | N26: =ROUND(I26*J26*(1-K26),0)
A27: T05-250102-075999 | B27: 45659 | C27: 17:27 | D27: Magasin 5 — Kaya Marché | E27: Adama Bationo | F27: 8234 | G27: Casque de chantier — réf 2 | H27: Consommables | I27: 27 | J27: 5400 | K27: 0 | L27: 145800 | M27: 172044 | N27: =ROUND(I27*J27*(1-K27),0)
A28: T05-250102-076000 | B28: 45659 | C28: 08:18 | D28: Magasin 5 — Kaya Marché | E28: Boureima Ouédraogo | F28: 5812 | G28: Tableau 18 modules — réf 1 | H28: Electricité | I28: 25 | J28: 8700 | K28: 0.08 | L28: 200100 | M28: 236118 | N28: =ROUND(I28*J28*(1-K28),0)
A29: T05-250102-076001 | B29: 45659 | C29: 07:43 | D29: Magasin 5 — Kaya Marché | E29: Moussa Ilboudo | F29: 9745 | G29: Pavé autobloquant — réf 2 | H29: Matériaux | I29: 3 | J29: 675 | K29: 0 | L29: 2025 | M29: 2389 | N29: =ROUND(I29*J29*(1-K29),0)
A30: T05-250102-076002 | B30: 45659 | C30: 10:32 | D30: Magasin 5 — Kaya Marché | E30: Salamatu Sankara | F30: 21264 | G30: Mètre ruban 5 m — réf 1 | H30: Quincaillerie | I30: 12 | J30: 7475 | K30: 0.04 | L30: 86112 | M30: 101612 | N30: =ROUND(I30*J30*(1-K30),0)
A31: T05-250102-076003 | B31: 45659 | C31: 10:37 | D31: Magasin 5 — Kaya Marché | E31: Boureima Ouédraogo | F31: 20263 | G31: Ciment CPJ45 50 kg — réf 1 | H31: Matériaux | I31: 1 | J31: 6100 | K31: 0 | L31: 6100 | M31: 7198 | N31: =ROUND(I31*J31*(1-K31),0)
A32: T05-250102-076004 | B32: 45659 | C32: 07:12 | D32: Magasin 5 — Kaya Marché | E32: Salamatu Sankara | G32: Tube PVC évacuation 100 mm (ml) — réf 1 | H32: Plomberie | I32: 5 | J32: 3500 | K32: 0 | L32: 17500 | M32: 20650 | N32: =ROUND(I32*J32*(1-K32),0)
A33: T05-250102-076005 | B33: 45659 | C33: 08:40 | D33: Magasin 5 — Kaya Marché | E33: Boureima Ouédraogo | F33: 16610 | G33: Peinture glycéro 1 L — réf 2 | H33: Peinture | I33: 17 | J33: 3925 | K33: 0 | L33: 66725 | M33: 78735 | N33: =ROUND(I33*J33*(1-K33),0)
A34: T05-250102-076006 | B34: 45659 | C34: 12:58 | D34: Magasin 5 — Kaya Marché | E34: Boureima Ouédraogo | G34: Colle à carrelage 25 kg — réf 2 | H34: Matériaux | I34: 5 | J34: 4300 | K34: 0.04 | L34: 20640 | M34: 24355 | N34: =ROUND(I34*J34*(1-K34),0)
A35: T05-250102-076007 | B35: 45659 | C35: 18:53 | D35: Magasin 5 — Kaya Marché | E35: Adama Bationo | F35: 2691 | G35: Raccord laiton 20/27 — réf 2 | H35: Plomberie | I35: 4 | J35: 4825 | K35: 0.04 | L35: 18528 | M35: 21863 | N35: =ROUND(I35*J35*(1-K35),0)
A36: T05-250102-076008 | B36: 45659 | C36: 14:52 | D36: Magasin 5 — Kaya Marché | E36: Salamatu Sankara | F36: 16233 | G36: Pelle carrée — réf 2 | H36: Consommables | I36: 2 | J36: 5100 | K36: 0 | L36: 10200 | M36: 12036 | N36: =ROUND(I36*J36*(1-K36),0)
A37: T05-250102-076009 | B37: 45659 | C37: 16:14 | D37: Magasin 5 — Kaya Marché | E37: Boureima Ouédraogo | F37: 2178 | G37: Sac de transport 100 kg — réf 1 | H37: Consommables | I37: 2 | J37: 8775 | K37: 0.04 | L37: 16848 | M37: 19881 | N37: =ROUND(I37*J37*(1-K37),0)
A38: T05-250102-076010 | B38: 45659 | C38: 12:34 | D38: Magasin 5 — Kaya Marché | E38: Salamatu Sankara | F38: 12170 | G38: Brique de terre cuite — réf 2 | H38: Matériaux | I38: 2 | J38: 675 | K38: 0 | L38: 1350 | M38: 1593 | N38: =ROUND(I38*J38*(1-K38),0)
A39: T05-250102-076011 | B39: 45659 | C39: 18:01 | D39: Magasin 5 — Kaya Marché | E39: Moussa Ilboudo | F39: 2474 | G39: Tout-venant (m3) — réf 1 | H39: Matériaux | I39: 4 | J39: 16375 | K39: 0.04 | L39: 62880 | M39: 74198 | N39: =ROUND(I39*J39*(1-K39),0)
A40: T05-250102-076012 | B40: 45659 | C40: 13:31 | D40: Magasin 5 — Kaya Marché | E40: Adama Bationo | F40: 4653 | G40: Parpaing 15 aggloméré — réf 2 | H40: Matériaux | I40: 5 | J40: 1400 | K40: 0 | L40: 7000 | M40: 8260 | N40: =ROUND(I40*J40*(1-K40),0)
A41: T05-250102-076013 | B41: 45659 | C41: 12:57 | D41: Magasin 5 — Kaya Marché | E41: Salamatu Sankara | F41: 7529 | G41: Régulateur de charge 10 A — réf 1 | H41: Electricité | I41: 3 | J41: 21675 | K41: 0.03 | L41: 63074 | M41: 74427 | N41: =ROUND(I41*J41*(1-K41),0)
A42: T05-250201-079456 | B42: 45689 | C42: 13:52 | D42: Magasin 5 — Kaya Marché | E42: Boureima Ouédraogo | F42: 3742 | G42: Té fonte 100 — réf 1 | H42: Plomberie | I42: 1 | J42: 3150 | K42: 0.04 | L42: 3024 | M42: 3568 | N42: =ROUND(I42*J42*(1-K42),0)
A43: T05-250201-079457 | B43: 45689 | C43: 09:27 | D43: Magasin 5 — Kaya Marché | E43: Moussa Ilboudo | F43: 0 | G43: Peinture glycéro 1 L — réf 1 | H43: Peinture | I43: 21 | J43: 3300 | K43: 0 | L43: 69300 | M43: 81774 | N43: =ROUND(I43*J43*(1-K43),0)
A44: T05-250201-079458 | B44: 45689 | C44: 18:28 | D44: Magasin 5 — Kaya Marché | E44: Salamatu Sankara | F44: 21909 | G44: Carreau de pavement 40x40 — réf 1 | H44: Matériaux | I44: 4 | J44: 1025 | K44: 0 | L44: 4100 | M44: 4838 | N44: =ROUND(I44*J44*(1-K44),0)
A45: T05-250201-079459 | B45: 45689 | C45: 16:55 | D45: Magasin 5 — Kaya Marché | E45: Moussa Ilboudo | F45: 21680 | G45: Lampe solaire murale — réf 1 | H45: Electricité | I45: 5 | J45: 10525 | K45: 0.03 | L45: 51046 | M45: 60234 | N45: =ROUND(I45*J45*(1-K45),0)
A46: T05-250201-079460 | B46: 45689 | C46: 18:22 | D46: Magasin 5 — Kaya Marché | E46: Salamatu Sankara | F46: 1519 | G46: Colle à carrelage 25 kg — réf 1 | H46: Matériaux | I46: 8 | J46: 6100 | K46: 0.04 | L46: 46848 | M46: 55281 | N46: =ROUND(I46*J46*(1-K46),0)
... A73: T05-250203-079681 | B73: 45691 | C73: 07:33 | D73: Magasin 5 — Kaya Marché | E73: Salamatu Sankara | F73: 23278 | G73: Antirouille rouge brique 1 L — réf 2 | H73: Peinture | I73: 3 | J73: 6800 | K73: 0.03 | L73: 19788 | M73: 23350 | N73: =ROUND(I73*J73*(1-K73),0)
A74: T05-250203-079682 | B74: 45691 | C74: 16:45 | D74: Magasin 5 — Kaya Marché | E74: Moussa Ilboudo | G74: Gants anti-coupure (paire) — réf 1 | H74: Consommables | I74: 6 | J74: 8925 | K74: 0 | L74: 53550 | M74: 63189 | N74: =ROUND(I74*J74*(1-K74),0)
A75: T05-250203-079683 | B75: 45691 | C75: 10:30 | D75: Magasin 5 — Kaya Marché | E75: Salamatu Sankara | F75: 9467 | G75: Clé plate 13 — réf 1 | H75: Quincaillerie | I75: 3 | J75: 9725 | K75: 0 | L75: 29175 | M75: 34427 | N75: =ROUND(I75*J75*(1-K75),0)
A76: T05-250203-079684 | B76: 45691 | C76: 11:32 | D76: Magasin 5 — Kaya Marché | E76: Salamatu Sankara | F76: 11926 | G76: Brique de terre cuite — réf 1 | H76: Matériaux | I76: 4 | J76: 1050 | K76: 0.04 | L76: 4032 | M76: 4758 | N76: =ROUND(I76*J76*(1-K76),0)
A77: T05-250203-079685 | B77: 45691 | C77: 15:11 | D77: Magasin 5 — Kaya Marché | E77: Salamatu Sankara | F77: 756 | G77: Carreau de pavement 40x40 — réf 1 | H77: Matériaux | I77: 5 | J77: 1075 | K77: 0 | L77: 5375 | M77: 6343 | N77: =ROUND(I77*J77*(1-K77),0)
A78: T05-250203-079686 | B78: 45691 | C78: 14:03 | D78: Magasin 5 — Kaya Marché | E78: Moussa Ilboudo | F78: 5532 | G78: Vernis marin 1 L — réf 1 | H78: Peinture | I78: 6 | J78: 5800 | K78: 0 | L78: 34800 | M78: 41064 | N78: =ROUND(I78*J78*(1-K78),0)
A79: T05-250203-079687 | B79: 45691 | C79: 18:08 | D79: Magasin 5 — Kaya Marché | E79: Adama Bationo | F79: 22119 | G79: Bêche à manche bois — réf 1 | H79: Consommables | I79: 4 | J79: 5175 | K79: 0 | L79: 20700 | M79: 24426 | N79: =ROUND(I79*J79*(1-K79),0)
A80: T05-250203-079688 | B80: 45691 | C80: 17:18 | D80: Magasin 5 — Kaya Marché | E80: Adama Bationo | F80: 10043 | G80: Gravier 15/25 (m3) — réf 1 | H80: Matériaux | I80: 2 | J80: 31200 | K80: 0.08 | L80: 57408 | M80: 67741 | N80: =ROUND(I80*J80*(1-K80),0)
A81: T05-250203-079689 | B81: 45691 | C81: 09:39 | D81: Magasin 5 — Kaya Marché | E81: Boureima Ouédraogo | F81: 14715 | G81: Robinet mitigeur évier — réf 2 | H81: Plomberie | I81: 5 | J81: 36200 | K81: 0.04 | L81: 173760 | M81: 205037 | N81: =ROUND(I81*J81*(1-K81),0)
A82: T05-250301-082692 | B82: 45717 | C82: 13:52 | D82: Magasin 5 — Kaya Marché | E82: Moussa Ilboudo | F82: 19875 | G82: Tournevis cruciforme PH2 — réf 1 | H82: Quincaillerie | I82: 3 | J82: 8200 | K82: 0.04 | L82: 23616 | M82: 27867 | N82: =ROUND(I82*J82*(1-K82),0)
A83: T05-250301-082693 | B83: 45717 | C83: 18:17 | D83: Magasin 5 — Kaya Marché | E83: Salamatu Sankara | F83: 12170 | G83: Diluant nitro 5 L — réf 2 | H83: Peinture | I83: 27 | J83: 4375 | K83: 0 | L83: 118125 | M83: 139387 | N83: =ROUND(I83*J83*(1-K83),0)
A84: T05-250301-082694 | B84: 45717 | C84: 15:12 | D84: Magasin 5 — Kaya Marché | E84: Salamatu Sankara | F84: 19501 | G84: Parpaing 15 aggloméré — réf 1 | H84: Matériaux | I84: 2 | J84: 1500 | K84: 0.04 | L84: 2880 | M84: 3398 | N84: =ROUND(I84*J84*(1-K84),0)
A85: T05-250301-082695 | B85: 45717 | C85: 12:20 | D85: Magasin 5 — Kaya Marché | E85: Moussa Ilboudo | F85: 5578 | G85: Pavé autobloquant — réf 2 | H85: Matériaux | I85: 2 | J85: 675 | K85: 0.03 | L85: 1310 | M85: 1546 | N85: =ROUND(I85*J85*(1-K85),0)
A86: T05-250301-082696 | B86: 45717 | C86: 15:07 | D86: Magasin 5 — Kaya Marché | E86: Adama Bationo | F86: 6420 | G86: Brique de terre cuite — réf 2 | H86: Matériaux | I86: 1 | J86: 675 | K86: 0 | L86: 675 | M86: 797 | N86: =ROUND(I86*J86*(1-K86),0)
... A111: T05-250302-082744 | B111: 45718 | C111: 08:47 | D111: Magasin 5 — Kaya Marché | E111: Boureima Ouédraogo | F111: 3668 | G111: Marteau de menuisier — réf 2 | H111: Quincaillerie | I111: 4 | J111: 8725 | K111: 0 | L111: 34900 | M111: 41182 | N111: =ROUND(I111*J111*(1-K111),0)
A112: T05-250302-082745 | B112: 45718 | C112: 11:13 | D112: Magasin 5 — Kaya Marché | E112: Adama Bationo | G112: Tout-venant (m3) — réf 1 | H112: Matériaux | I112: 9 | J112: 16475 | K112: 0 | L112: 148275 | M112: 174965 | N112: =ROUND(I112*J112*(1-K112),0)
A113: T05-250302-082745 | B113: 45718 | C113: 11:52 | D113: Magasin 5 — Kaya Marché | E113: Adama Bationo | F113: 19185 | G113: Lampe solaire murale — réf 1 | H113: Electricité | I113: 3 | J113: 10175 | K113: 0 | L113: 30525 | M113: 36019 | N113: =ROUND(I113*J113*(1-K113),0)
A114: T05-250303-082910 | B114: 45719 | C114: 08:03 | D114: Magasin 5 — Kaya Marché | E114: Moussa Ilboudo | F114: 0 | G114: Marteau de menuisier — réf 2 | H114: Quincaillerie | I114: 1 | J114: 8775 | K114: 0 | L114: 8775 | M114: 10355 | N114: =ROUND(I114*J114*(1-K114),0)
A115: T05-250303-082910 | B115: 45719 | C115: 16:39 | D115: Magasin 5 — Kaya Marché | E115: Salamatu Sankara | F115: 4415 | G115: Tableau 18 modules — réf 2 | H115: Electricité | I115: 1 | J115: 9075 | K115: 0 | L115: 9075 | M115: 10709 | N115: =ROUND(I115*J115*(1-K115),0)
A116: T05-250303-082911 | B116: 45719 | C116: 07:06 | D116: Magasin 5 — Kaya Marché | E116: Salamatu Sankara | F116: 13669 | G116: Brouette 90 L — réf 2 | H116: Consommables | I116: 1 | J116: 9875 | K116: 0 | L116: 9875 | M116: 11653 | N116: =ROUND(I116*J116*(1-K116),0)
A117: T05-250303-082911 | B117: 45719 | C117: 09:44 | D117: Magasin 5 — Kaya Marché | E117: Salamatu Sankara | F117: 5228 | G117: Marteau de menuisier — réf 1 | H117: Quincaillerie | I117: 8 | J117: 9400 | K117: 0.08 | L117: 69184 | M117: 81637 | N117: =ROUND(I117*J117*(1-K117),0)
A118: T05-250303-082912 | B118: 45719 | C118: 08:38 | D118: Magasin 5 — Kaya Marché | E118: Salamatu Sankara | F118: 16351 | G118: Panneau solaire 100 W — réf 2 | H118: Electricité | I118: 1 | J118: 15575 | K118: 0.03 | L118: 15108 | M118: 17827 | N118: =ROUND(I118*J118*(1-K118),0)
A119: T05-250303-082912 | B119: 45719 | C119: 08:47 | D119: Magasin 5 — Kaya Marché | E119: Salamatu Sankara | F119: 9672 | G119: Tournevis cruciforme PH2 — réf 1 | H119: Quincaillerie | I119: 13 | J119: 7900 | K119: 0.04 | L119: 98592 | M119: 116339 | N119: =ROUND(I119*J119*(1-K119),0)
A120: T05-250303-082913 | B120: 45719 | C120: 16:01 | D120: Magasin 5 — Kaya Marché | E120: Adama Bationo | F120: 22643 | G120: Robinet mitigeur évier — réf 1 | H120: Plomberie | I120: 26 | J120: 33375 | K120: 0.04 | L120: 833040 | M120: 982987 | N120: =ROUND(I120*J120*(1-K120),0)
A121: T05-250303-082913 | B121: 45719 | C121: 16:03 | D121: Magasin 5 — Kaya Marché | E121: Salamatu Sankara | F121: 640 | G121: Pavé autobloquant — réf 2 | H121: Matériaux | I121: 2 | J121: 700 | K121: 0 | L121: 1400 | M121: 1652 | N121: =ROUND(I121*J121*(1-K121),0)
A122: T05-250401-086352 | B122: 45748 | C122: 11:01 | D122: Magasin 5 — Kaya Marché | E122: Boureima Ouédraogo | F122: 0 | G122: Échelle aluminium 4 marches — réf 1 | H122: Consommables | I122: 3 | J122: 8650 | K122: 0 | L122: 25950 | M122: 30621 | N122: =ROUND(I122*J122*(1-K122),0)
A123: T05-250401-086353 | B123: 45748 | C123: 12:45 | D123: Magasin 5 — Kaya Marché | E123: Moussa Ilboudo | F123: 13771 | G123: Plaque de plâtre 13 mm — réf 2 | H123: Bois & panneaux | I123: 4 | J123: 13900 | K123: 0.04 | L123: 53376 | M123: 62984 | N123: =ROUND(I123*J123*(1-K123),0)
A124: T05-250401-086354 | B124: 45748 | C124: 12:37 | D124: Magasin 5 — Kaya Marché | E124: Moussa Ilboudo | F124: 19670 | G124: Écrou hexagonal 10 (sachet) — réf 2 | H124: Quincaillerie | I124: 3 | J124: 2200 | K124: 0.04 | L124: 6336 | M124: 7476 | N124: =ROUND(I124*J124*(1-K124),0)
... A127: T05-250401-086357 | B127: 45748 | C127: 13:18 | D127: Magasin 5 — Kaya Marché | E127: Adama Bationo | F127: 22824 | G127: Chasse d'eau 6 L — réf 1 | H127: Plomberie | I127: -5 | J127: 26625 | K127: 0.04 | L127: -127800 | M127: -150804 | N127: =ROUND(I127*J127*(1-K127),0)
A128: T05-250401-086358 | B128: 45748 | C128: 17:48 | D128: Magasin 5 — Kaya Marché | E128: Boureima Ouédraogo | G128: Tube PER 16x2 (rouleau) — réf 2 | H128: Plomberie | I128: 3 | J128: 3300 | K128: 0 | L128: 9900 | M128: 11682 | N128: =ROUND(I128*J128*(1-K128),0)
A129: T05-250401-086359 | B129: 45748 | C129: 18:04 | D129: Magasin 5 — Kaya Marché | E129: Adama Bationo | F129: 0 | G129: Tube PVC évacuation 100 mm (ml) — réf 1 | H129: Plomberie | I129: 2 | J129: 3475 | K129: 0 | L129: 6950 | M129: 8201 | N129: =ROUND(I129*J129*(1-K129),0)
A130: T05-250401-086360 | B130: 45748 | C130: 08:47 | D130: Magasin 5 — Kaya Marché | E130: Salamatu Sankara | F130: 20670 | G130: Enduit de rebouchage 5 kg — réf 1 | H130: Peinture | I130: 11 | J130: 4225 | K130: 0 | L130: 46475 | M130: 54841 | N130: =ROUND(I130*J130*(1-K130),0)
A131: T05-250401-086361 | B131: 45748 | C131: 10:42 | D131: Magasin 5 — Kaya Marché | E131: Adama Bationo | G131: Coude PVC 90° 100 — réf 1 | H131: Plomberie | I131: 3 | J131: 4075 | K131: 0 | L131: 12225 | M131: 14425 | N131: =ROUND(I131*J131*(1-K131),0)
A132: T05-250401-086362 | B132: 45748 | C132: 16:34 | D132: Magasin 5 — Kaya Marché | E132: Boureima Ouédraogo | F132: 2446 | G132: Peinture glycéro 1 L — réf 1 | H132: Peinture | I132: 12 | J132: 3250 | K132: 0 | L132: 39000 | M132: 46020 | N132: =ROUND(I132*J132*(1-K132),0)
A133: T05-250401-086363 | B133: 45748 | C133: 15:34 | D133: Magasin 5 — Kaya Marché | E133: Moussa Ilboudo | F133: 12082 | G133: Sac de transport 100 kg — réf 1 | H133: Consommables | I133: 2 | J133: 8650 | K133: 0.04 | L133: 16608 | M133: 19597 | N133: =ROUND(I133*J133*(1-K133),0)
A134: T05-250401-086364 | B134: 45748 | C134: 11:16 | D134: Magasin 5 — Kaya Marché | E134: Salamatu Sankara | F134: 367 | G134: Hourdis creux 12 — réf 2 | H134: Matériaux | I134: 4 | J134: 1500 | K134: 0.04 | L134: 5760 | M134: 6797 | N134: =ROUND(I134*J134*(1-K134),0)
A135: T05-250401-086365 | B135: 45748 | C135: 15:20 | D135: Magasin 5 — Kaya Marché | E135: Adama Bationo | F135: 0 | G135: Gravier 15/25 (m3) — réf 1 | H135: Matériaux | I135: 5 | J135: 30550 | K135: 0 | L135: 152750 | M135: 180245 | N135: =ROUND(I135*J135*(1-K135),0)
A136: T05-250401-086366 | B136: 45748 | C136: 10:34 | D136: Magasin 5 — Kaya Marché | E136: Adama Bationo | F136: 2661 | G136: Douche de toilettes — réf 2 | H136: Plomberie | I136: 13 | J136: 30850 | K136: 0 | L136: 401050 | M136: 473239 | N136: =ROUND(I136*J136*(1-K136),0)
A137: T05-250401-086367 | B137: 45748 | C137: 12:11 | D137: Magasin 5 — Kaya Marché | E137: Boureima Ouédraogo | F137: 12489 | G137: Pavé autobloquant — réf 1 | H137: Matériaux | I137: 1 | J137: 1125 | K137: 0 | L137: 1125 | M137: 1327 | N137: =ROUND(I137*J137*(1-K137),0)
A138: T05-250401-086368 | B138: 45748 | C138: 10:06 | D138: Magasin 5 — Kaya Marché | E138: Boureima Ouédraogo | F138: 9106 | G138: Tout-venant (m3) — réf 2 | H138: Matériaux | I138: 5 | J138: 23400 | K138: 0 | L138: 117000 | M138: 138060 | N138: =ROUND(I138*J138*(1-K138),0)
A139: T05-250401-086369 | B139: 45748 | C139: 12:57 | D139: Magasin 5 — Kaya Marché | E139: Boureima Ouédraogo | F139: 21755 | G139: Perforateur 800 W — réf 1 | H139: Quincaillerie | I139: 2 | J139: 8000 | K139: 0.08 | L139: 14720 | M139: 17370 | N139: =ROUND(I139*J139*(1-K139),0)
A140: T05-250401-086370 | B140: 45748 | C140: 13:30 | D140: Magasin 5 — Kaya Marché | E140: Moussa Ilboudo | F140: 0 | G140: Perforateur 800 W — réf 2 | H140: Quincaillerie | I140: 2 | J140: 5800 | K140: 0 | L140: 11600 | M140: 13688 | N140: =ROUND(I140*J140*(1-K140),0)
A141: T05-250401-086371 | B141: 45748 | C141: 17:32 | D141: Magasin 5 — Kaya Marché | E141: Adama Bationo | F141: 3959 | G141: Passe-câble étanche — réf 1 | H141: Electricité | I141: 2 | J141: 16775 | K141: 0 | L141: 33550 | M141: 39589 | N141: =ROUND(I141*J141*(1-K141),0)
A142: T05-250401-086372 | B142: 45748 | C142: 16:07 | D142: Magasin 5 — Kaya Marché | E142: Adama Bationo | F142: 18885 | G142: Sable de rivière (m3) — réf 1 | H142: Matériaux | I142: 4 | J142: 25975 | K142: 0 | L142: 103900 | M142: 122602 | N142: =ROUND(I142*J142*(1-K142),0)
A143: T05-250401-086373 | B143: 45748 | C143: 17:07 | D143: Magasin 5 — Kaya Marché | E143: Adama Bationo | F143: 22027 | G143: Cheville nylon 8 mm (sachet) — réf 2 | H143: Quincaillerie | I143: 11 | J143: 2175 | K143: 0.04 | L143: 22968 | M143: 27102 | N143: =ROUND(I143*J143*(1-K143),0)
A144: T05-250401-086374 | B144: 45748 | C144: 11:48 | D144: Magasin 5 — Kaya Marché | E144: Salamatu Sankara | G144: Cheville nylon 8 mm (sachet) — réf 2 | H144: Quincaillerie | I144: 5 | J144: 2150 | K144: 0 | L144: 10750 | M144: 12685 | N144: =ROUND(I144*J144*(1-K144),0)
A145: T05-250401-086375 | B145: 45748 | C145: 15:23 | D145: Magasin 5 — Kaya Marché | E145: Moussa Ilboudo | F145: 5345 | G145: Pince coupante 200 mm — réf 1 | H145: Quincaillerie | I145: -3 | J145: 5200 | K145: 0 | L145: -15600 | M145: -18408 | N145: =ROUND(I145*J145*(1-K145),0)
A146: T05-250401-086376 | B146: 45748 | C146: 16:39 | D146: Magasin 5 — Kaya Marché | E146: Moussa Ilboudo | F146: 19650 | G146: Bêche à manche bois — réf 2 | H146: Consommables | I146: -3 | J146: 5800 | K146: 0.04 | L146: -16704 | M146: -19711 | N146: =ROUND(I146*J146*(1-K146),0)
A147: T05-250401-086377 | B147: 45748 | C147: 11:37 | D147: Magasin 5 — Kaya Marché | E147: Adama Bationo | F147: 23136 | G147: Tableau 18 modules — réf 1 | H147: Electricité | I147: 3 | J147: 8775 | K147: 0.04 | L147: 25272 | M147: 29821 | N147: =ROUND(I147*J147*(1-K147),0)
A148: T05-250401-086378 | B148: 45748 | C148: 16:36 | D148: Magasin 5 — Kaya Marché | E148: Adama Bationo | F148: 15288 | G148: Scie égoïne 500 mm — réf 1 | H148: Quincaillerie | I148: 4 | J148: 10975 | K148: 0 | L148: 43900 | M148: 51802 | N148: =ROUND(I148*J148*(1-K148),0)
A149: T05-250401-086379 | B149: 45748 | C149: 16:47 | D149: Magasin 5 — Kaya Marché | E149: Salamatu Sankara | F149: 9940 | G149: Hourdis creux 12 — réf 2 | H149: Matériaux | I149: 4 | J149: 1550 | K149: 0 | L149: 6200 | M149: 7316 | N149: =ROUND(I149*J149*(1-K149),0)
A150: T05-250401-086380 | B150: 45748 | C150: 17:13 | D150: Magasin 5 — Kaya Marché | E150: Salamatu Sankara | F150: 11981 | G150: Tournevis cruciforme PH2 — réf 1 | H150: Quincaillerie | I150: 10 | J150: 8200 | K150: 0 | L150: 82000 | M150: 96760 | N150: =ROUND(I150*J150*(1-K150),0)
A151: T05-250402-086501 | B151: 45749 | C151: 08:43 | D151: Magasin 5 — Kaya Marché | E151: Adama Bationo | F151: 19457 | G151: Brouette 90 L — réf 2 | H151: Consommables | I151: 7 | J151: 10125 | K151: 0.03 | L151: 68749 | M151: 81124 | N151: =ROUND(I151*J151*(1-K151),0)
A152: T05-250402-086501 | B152: 45749 | C152: 10:29 | D152: Magasin 5 — Kaya Marché | E152: Salamatu Sankara | F152: 7706 | G152: Peinture glycéro 1 L — réf 2 | H152: Peinture | I152: 16 | J152: 3900 | K152: 0.04 | L152: 59904 | M152: 70687 | N152: =ROUND(I152*J152*(1-K152),0)
A153: T05-250402-086502 | B153: 45749 | C153: 17:58 | D153: Magasin 5 — Kaya Marché | E153: Salamatu Sankara | F153: 8920 | G153: Chasse d'eau 6 L — réf 1 | H153: Plomberie | I153: 3 | J153: 25900 | K153: 0.04 | L153: 74592 | M153: 88019 | N153: =ROUND(I153*J153*(1-K153),0)
A154: T05-250402-086502 | B154: 45749 | C154: 08:11 | D154: Magasin 5 — Kaya Marché | E154: Adama Bationo | F154: 6563 | G154: Écrou hexagonal 10 (sachet) — réf 1 | H154: Quincaillerie | I154: -4 | J154: 1450 | K154: 0.04 | L154: -5568 | M154: -6570 | N154: =ROUND(I154*J154*(1-K154),0)
A155: T05-250402-086503 | B155: 45749 | C155: 18:21 | D155: Magasin 5 — Kaya Marché | E155: Salamatu Sankara | F155: 2883 | G155: Gravier 15/25 (m3) — réf 1 | H155: Matériaux | I155: 4 | J155: 30950 | K155: 0.08 | L155: 113896 | M155: 134397 | N155: =ROUND(I155*J155*(1-K155),0)
A156: T05-250402-086503 | B156: 45749 | C156: 18:23 | D156: Magasin 5 — Kaya Marché | E156: Salamatu Sankara | F156: 14971 | G156: Ciment CPJ45 50 kg — réf 2 | H156: Matériaux | I156: 17 | J156: 6475 | K156: 0.04 | L156: 105672 | M156: 124693 | N156: =ROUND(I156*J156*(1-K156),0)
... A172: T05-250501-090472 | B172: 45778 | C172: 15:40 | D172: Magasin 5 — Kaya Marché | E172: Boureima Ouédraogo | F172: 14106 | G172: Pince coupante 200 mm — réf 2 | H172: Quincaillerie | I172: 2 | J172: 10500 | K172: 0.04 | L172: 20160 | M172: 23789 | N172: =ROUND(I172*J172*(1-K172),0)
A173: T05-250501-090472 | B173: 45778 | C173: 09:38 | D173: Magasin 5 — Kaya Marché | E173: Adama Bationo | G173: Chasse d'eau 6 L — réf 1 | H173: Plomberie | I173: 3 | J173: 26075 | K173: 0 | L173: 78225 | M173: 92305 | N173: =ROUND(I173*J173*(1-K173),0)
...

Sheet produits
A1: id_produit | B1: designation | C1: categorie | D1: sous_categorie | E1: unite | F1: prix_vente_ht | G1: poids_unite_kg | H1: fournisseur | I1: reference_fournisseur | J1: tva | K1: actif
A2: 1 | B2: Ciment CPJ45 50 kg — réf 1 | C2: Matériaux | D2: Ciment & liants | E2: sac | F2: 5200 | G2: 33.17 | H2: CIMAF Sahel | I2: MAT-0001 | J2: 0.18 | K2: 1
A3: 2 | B3: Ciment CPJ45 50 kg — réf 2 | C3: Matériaux | D3: Ciment & liants | E3: sac | F3: 5575 | G3: 28.24 | H3: CIMAF Sahel | I3: MAT-0002 | J3: 0.18 | K3: 1
A4: 3 | B4: Ciment CPJ35 50 kg — réf 1 | C4: Matériaux | D4: Ciment & liants | E4: sac | F4: 5275 | G4: 55.6 | H4: CIMAF Sahel | I4: MAT-0003 | J4: 0.18 | K4: 1
A5: 4 | B5: Ciment CPJ35 50 kg — réf 2 | C5: Matériaux | D5: Ciment & liants | E5: sac | F5: 3550 | G5: 32.68 | H5: CIMAF Sahel | I5: MAT-0004 | J5: 0.18 | K5: 1
A6: 5 | B6: Chaux aérienne 25 kg — réf 1 | C6: Matériaux | D6: Ciment & liants | E6: sac | F6: 4400 | G6: 26.29 | H6: CIMAF Sahel | I6: MAT-0005 | J6: 0.18 | K6: 1
A7: 6 | B7: Chaux aérienne 25 kg — réf 2 | C7: Matériaux | D7: Ciment & liants | E7: sac | F7: 6925 | G7: 59.63 | H7: CIMAF Sahel | I7: MAT-0006 | J7: 0.18 | K7: 1
A8: 7 | B8: Plâtre de construction 25 kg — réf 1 | C8: Matériaux | D8: Ciment & liants | E8: sac | F8: 3750 | G8: 33.06 | H8: CIMAF Sahel | I8: MAT-0007 | J8: 0.18 | K8: 1
A9: 8 | B9: Plâtre de construction 25 kg — réf 2 | C9: Matériaux | D9: Ciment & liants | E9: sac | F9: 5150 | G9: 67.68 | H9: CIMAF Sahel | I9: MAT-0008 | J9: 0.18 | K9: 1
A10: 9 | B10: Colle à carrelage 25 kg — réf 1 | C10: Matériaux | D10: Ciment & liants | E10: sac | F10: 5075 | G10: 38.98 | H10: CIMAF Sahel | I10: MAT-0009 | J10: 0.18 | K10: 1
A11: 10 | B11: Colle à carrelage 25 kg — réf 2 | C11: Matériaux | D11: Ciment & liants | E11: sac | F11: 3775 | G11: 34.15 | H11: CIMAF Sahel | I11: MAT-0010 | J11: 0.18 | K11: 1
A12: 11 | B12: Enduit de lissage 20 kg — réf 1 | C12: Matériaux | D12: Ciment & liants | E12: sac | F12: 6300 | G12: 47.56 | H12: CIMAF Sahel | I12: MAT-0011 | J12: 0.18 | K12: 1
A13: 12 | B13: Enduit de lissage 20 kg — réf 2 | C13: Matériaux | D13: Ciment & liants | E13: sac | F13: 5500 | G13: 56.29 | H13: CIMAF Sahel | I13: MAT-0012 | J13: 0.18 | K13: 1
... A155: 154 | B155: Casque de chantier — réf 2 | C155: Consommables | D155: Divers chantier | E155: unité | F155: 4675 | G155: 0.36 | H155: EPI Faso | I155: CON-0154 | J155: 0.18 | K155: 1

Sheet clients
A1: id_client | B1: nom | C1: type_client | D1: ville | E1: region | F1: telephone | G1: email | H1: date_creation | I1: segment | J1: conditions_paiement | K1: plafond_credit
A2: 125 | B2: SARL g | C2: Professionnel | D2: Kaya | E2: Centre-Nord | F2: +226 78 38 90 25 54 | G2: contact125@entreprise.bf | H2: 2020-09-13 | I2: Standard | J2: 30 j | K2: 0
A3: 182 | B3: Menage 00182 | C3: Particulier | D3: Ziniaré | E3: Plateau-Central | F3: +226 74 35 48 20 75 | H3: 2016-04-20 | I3: Standard | J3: Comptant | K3: 0
A4: 246 | B4: Ets o | C4: Professionnel | D4: Ouagadougou | E4: Centre | F4: +226 79 44 35 43 60 | G4: contact246@gmail.com | H4: 2016-10-16 | I4: Standard | J4: Comptant | K4: 250000
A5: 261 | B5: Chantiers o | C5: Professionnel | D5: Ziniaré | E5: Plateau-Central | F5: +226 71 11 37 22 57 | G5: contact261@gmail.com | H5: 2024-01-24 | I5: Standard | J5: Comptant | K5: 0
A6: 353 | B6: Menage 00353 | C6: Particulier | D6: Ouagadougou | E6: Centre | F6: +226 74 52 20 61 48 | H6: 2020-09-14 | I6: Standard | J6: Comptant | K6: 1500000
A7: 367 | B7: Chantiers o | C7: Entreprise | D7: Ouagadougou | E7: Centre | F7: +226 78 69 90 11 87 | G7: contact367@gmail.com | H7: 2020-05-04 | I7: Argent | J7: Comptant | K7: 0
A8: 475 | B8: Menage 00475 | C8: Particulier | D8: Bobo-Dioulasso | E8: Hauts-Bassins | F8: +226 74 86 77 42 69 | H8: 2021-07-30 | I8: Argent | J8: Comptant | K8: 1500000
A9: 557 | B9: Chantiers é | C9: Professionnel | D9: Ouagadougou | E9: Centre | F9: +226 70 47 24 43 96 | G9: contact557@yahoo.fr | H9: 2025-07-12 | I9: Standard | J9: 30 j | K9: 0
A10: 640 | B10: Menage 00640 | C10: Particulier | D10: Koudougou | E10: Centre-Ouest | F10: +226 72 50 85 25 80 | H10: 2016-05-03 | I10: Standard | J10: Comptant | K10: 250000
A11: 728 | B11: Menage 00728 | C11: Particulier | D11: Ouagadougou | E11: Centre | F11: +226 75 67 28 59 91 | H11: 2024-10-22 | I11: Or | J11: Comptant | K11: 1500000
A12: 756 | B12: Chantiers d | C12: Professionnel | D12: Ouagadougou | E12: Centre | F12: +226 74 30 29 17 11 | G12: contact756@entreprise.bf | H12: 2016-08-30 | I12: Standard | J12: Comptant | K12: 0
A13: 883 | B13: Menage 00883 | C13: Particulier | D13: Ziniaré | E13: Plateau-Central | F13: +226 72 83 12 97 41 | H13: 2016-01-07 | I13: Standard | J13: Comptant | K13: 0
A14: 984 | B14: Ets B | C14: Entreprise | D14: Ouagadougou | E14: Centre | F14: +226 71 73 97 10 77 | G14: contact984@yahoo.fr | H14: 2018-02-25 | I14: Argent | J14: 30 j | K14: 0
A15: 1056 | B15: Ets T | C15: Administration | D15: Ouagadougou | E15: Centre | F15: +226 73 79 65 73 74 | H15: 2023-05-01 | I15: Standard | J15: Comptant | K15: 0
A16: 1117 | B16: Menage 01117 | C16: Particulier | D16: Kaya | E16: Centre-Nord | F16: +226 75 34 21 77 74 | H16: 2018-02-09 | I16: Argent | J16: 30 j | K16: 1500000
A17: 1144 | B17: Menage 01144 | C17: Particulier | D17: Ouagadougou | E17: Centre | F17: +226 70 74 56 21 36 | H17: 2024-08-19 | I17: Argent | J17: 30 j | K17: 0
A18: 1242 | B18: Menage 01242 | C18: Particulier | D18: Kaya | E18: Centre-Nord | F18: +226 76 76 90 49 66 | H18: 2021-05-16 | I18: Argent | J18: Comptant | K18: 1500000
A19: 1357 | B19: Menage 01357 | C19: Particulier | D19: Bobo-Dioulasso | E19: Hauts-Bassins | F19: +226 78 46 29 79 29 | H19: 2019-08-23 | I19: Standard | J19: Comptant | K19: 250000
A20: 1359 | B20: Menage 01359 | C20: Particulier | D20: Ouagadougou | E20: Centre | F20: +226 70 73 77 42 18 | H20: 2016-12-08 | I20: Standard | J20: 60 j | K20: 1500000
A21: 1374 | B21: Menage 01374 | C21: Particulier | D21: Koudougou | E21: Centre-Ouest | F21: +226 72 78 11 29 47 | H21: 2018-03-04 | I21: Standard | J21: 30 j | K21: 500000
A22: 1455 | B22: Menage 01455 | C22: Particulier | D22: Bobo-Dioulasso | E22: Hauts-Bassins | F22: +226 70 31 23 16 71 | H22: 2023-11-24 | I22: Standard | J22: Comptant | K22: 500000
A23: 1462 | B23: Menage 01462 | C23: Particulier | D23: Bobo-Dioulasso | E23: Hauts-Bassins | F23: +226 72 19 36 45 64 | H23: 2016-02-08 | I23: Standard | J23: Comptant | K23: 0
A24: 1469 | B24: Menage 01469 | C24: Particulier | D24: Bobo-Dioulasso | E24: Hauts-Bassins | F24: +226 76 87 26 32 64 | H24: 2025-10-14 | I24: Standard | J24: 30 j | K24: 1500000
A25: 1472 | B25: Chantiers o | C25: Professionnel | D25: Bobo-Dioulasso | E25: Hauts-Bassins | F25: +226 71 32 10 75 74 | G25: contact1472@gmail.com | H25: 2022-07-27 | I25: Standard | J25: Comptant | K25: 1500000
A26: 1508 | B26: Menage 01508 | C26: Particulier | D26: Bobo-Dioulasso | E26: Hauts-Bassins | F26: +226 79 30 85 61 89 | H26: 2021-01-23 | I26: Standard | J26: Comptant | K26: 0
A27: 1519 | B27: Menage 01519 | C27: Particulier | D27: Ouagadougou | E27: Centre | F27: +226 76 29 34 40 89 | H27: 2017-03-16 | I27: Argent | J27: Comptant | K27: 0
A28: 1616 | B28: Ets K | C28: Entreprise | D28: Bobo-Dioulasso | E28: Hauts-Bassins | F28: +226 77 86 70 24 80 | H28: 2019-02-15 | I28: Argent | J28: Comptant | K28: 250000
A29: 1635 | B29: Menage 01635 | C29: Particulier | D29: Ouagadougou | E29: Centre | F29: +226 76 10 93 37 37 | H29: 2017-06-17 | I29: Argent | J29: 60 j | K29: 5000000
A30: 1690 | B30: Menage 01690 | C30: Particulier | D30: Ouagadougou | E30: Centre | F30: +226 75 50 26 72 87 | H30: 2019-09-03 | I30: Or | J30: Comptant | K30: 1500000
A31: 1716 | B31: Societe i | C31: Professionnel | D31: Ziniaré | E31: Plateau-Central | F31: +226 75 99 19 68 56 | G31: contact1716@entreprise.bf | H31: 2021-05-14 | I31: Standard | J31: Comptant | K31: 0
A32: 1796 | B32: Societe o | C32: Entreprise | D32: Ouagadougou | E32: Centre | F32: +226 75 13 46 56 40 | G32: contact1796@gmail.com | H32: 2024-09-17 | I32: Argent | J32: Comptant | K32: 0
A33: 1854 | B33: Menage 01854 | C33: Particulier | D33: Koudougou | E33: Centre-Ouest | F33: +226 70 91 13 31 26 | H33: 2024-04-04 | I33: Standard | J33: Comptant | K33: 1500000
A34: 1934 | B34: Chantiers b | C34: Professionnel | D34: Kaya | E34: Centre-Nord | F34: +226 70 32 99 64 82 | H34: 2023-05-06 | I34: Argent | J34: Comptant | K34: 0
A35: 2149 | B35: Menage 02149 | C35: Particulier | D35: Bobo-Dioulasso | E35: Hauts-Bassins | F35: +226 70 91 14 10 84 | H35: 2020-09-27 | I35: Standard | J35: Comptant | K35: 0
A36: 2150 | B36: Chantiers r | C36: Professionnel | D36: Kaya | E36: Centre-Nord | F36: +226 71 68 16 18 32 | G36: contact2150@outlook.fr | H36: 2023-11-14 | I36: Standard | J36: 30 j | K36: 0
A37: 2178 | B37: SARL O | C37: Entreprise | D37: Ouagadougou | E37: Centre | F37: +226 72 11 97 90 22 | H37: 2021-06-02 | I37: Argent | J37: Comptant | K37: 250000
A38: 2275 | B38: Menage 02275 | C38: Particulier | D38: Bobo-Dioulasso | E38: Hauts-Bassins | F38: +226 71 67 82 74 64 | H38: 2016-01-02 | I38: Standard | J38: 30 j | K38: 500000
A39: 2296 | B39: SARL p | C39: Professionnel | D39: Ziniaré | E39: Plateau-Central | F39: +226 75 39 79 92 52 | H39: 2020-09-14 | I39: Standard | J39: 60 j | K39: 1500000
A40: 2446 | B40: Menage 02446 | C40: Particulier | D40: Kaya | E40: Centre-Nord | F40: +226 72 86 99 51 84 | H40: 2016-07-01 | I40: Standard | J40: 30 j | K40: 250000
A41: 2474 | B41: SARL u | C41: Professionnel | D41: Kaya | E41: Centre-Nord | F41: +226 72 67 87 56 70 | G41: contact2474@entreprise.bf | H41: 2020-01-19 | I41: Argent | J41: Comptant | K41: 250000
A42: 2526 | B42: SARL u | C42: Professionnel | D42: Bobo-Dioulasso | E42: Hauts-Bassins | F42: +226 78 26 72 36 69 | G42: contact2526@entreprise.bf | H42: 2020-04-17 | I42: Standard | J42: Comptant | K42: 0
A43: 2656 | B43: Menage 02656 | C43: Particulier | D43: Ouagadougou | E43: Centre | F43: +226 72 40 22 97 85 | H43: 2026-02-21 | I43: Argent | J43: Comptant | K43: 0
A44: 2661 | B44: Ets r | C44: Entreprise | D44: Bobo-Dioulasso | E44: Hauts-Bassins | F44: +226 79 45 89 97 81 | G44: contact2661@entreprise.bf | H44: 2020-03-19 | I44: Standard | J44: Comptant | K44: 0
A45: 2691 | B45: Menage 02691 | C45: Particulier | D45: Ziniaré | E45: Plateau-Central | F45: +226 76 71 71 94 90 | H45: 2020-07-23 | I45: Argent | J45: 60 j | K45: 500000
A46: 2778 | B46: Ets o | C46: Professionnel | D46: Ouagadougou | E46: Centre | F46: +226 78 52 45 47 16 | H46: 2016-10-16 | I46: Standard | J46: Comptant | K46: 0
A47: 2883 | B47: Menage 02883 | C47: Particulier | D47: Ouagadougou | E47: Centre | F47: +226 74 32 50 81 75 | H47: 2022-05-21 | I47: Or | J47: Comptant | K47: 0
A48: 2988 | B48: SARL m | C48: Professionnel | D48: Koudougou | E48: Centre-Ouest | F48: +226 76 92 97 48 95 | H48: 2016-04-21 | I48: Standard | J48: Comptant | K48: 500000
A49: 3075 | B49: Chantiers r | C49: Professionnel | D49: Ouagadougou | E49: Centre | F49: +226 75 12 49 81 22 | H49: 2022-09-01 | I49: Standard | J49: 60 j | K49: 0
A50: 3371 | B50: Societe i | C50: Entreprise | D50: Bobo-Dioulasso | E50: Hauts-Bassins | F50: +226 76 86 61 11 84 | G50: contact3371@gmail.com | H50: 2022-03-24 | I50: Standard | J50: 30 j | K50: 0
A51: 3481 | B51: Societe o | C51: Entreprise | D51: Bobo-Dioulasso | E51: Hauts-Bassins | F51: +226 79 52 12 46 66 | G51: contact3481@outlook.fr | H51: 2022-11-26 | I51: Or | J51: Comptant | K51: 500000
A52: 3668 | B52: Menage 03668 | C52: Particulier | D52: Bobo-Dioulasso | E52: Hauts-Bassins | F52: +226 75 48 89 88 97 | H52: 2022-02-07 | I52: Standard | J52: Comptant | K52: 250000
A53: 3696 | B53: Ets s | C53: Professionnel | D53: Kaya | E53: Centre-Nord | F53: +226 71 71 23 71 45 | H53: 2022-09-25 | I53: Standard | J53: Comptant | K53: 250000
A54: 3702 | B54: Menage 03702 | C54: Particulier | D54: Ziniaré | E54: Plateau-Central | F54: +226 77 14 51 42 91 | H54: 2020-02-06 | I54: Standard | J54: Comptant | K54: 0
A55: 3742 | B55: SARL n | C55: Professionnel | D55: Kaya | E55: Centre-Nord | F55: +226 72 85 80 90 15 | G55: contact3742@entreprise.bf | H55: 2020-03-07 | I55: Argent | J55: 30 j | K55: 0
A56: 3764 | B56: Menage 03764 | C56: Particulier | D56: Bobo-Dioulasso | E56: Hauts-Bassins | F56: +226 72 27 95 23 66 | H56: 2024-08-18 | I56: Or | J56: Comptant | K56: 250000
A57: 3776 | B57: Chantiers p | C57: Entreprise | D57: Ouagadougou | E57: Centre | F57: +226 71 29 15 33 67 | G57: contact3776@yahoo.fr | H57: 2017-12-13 | I57: Or | J57: Comptant | K57: 250000
A58: 3800 | B58: Menage 03800 | C58: Particulier | D58: Ouagadougou | E58: Centre | F58: +226 79 16 25 94 47 | H58: 2021-06-05 | I58: Standard | J58: Comptant | K58: 250000
A59: 3818 | B59: Menage 03818 | C59: Particulier | D59: Ouagadougou | E59: Centre | F59: +226 73 91 79 86 87 | H59: 2019-01-02 | I59: Standard | J59: 30 j | K59: 500000
A60: 3825 | B60: Menage 03825 | C60: Particulier | D60: Ouagadougou | E60: Centre | F60: +226 74 48 29 62 48 | H60: 2025-04-05 | I60: Standard | J60: 30 j | K60: 1500000
A61: 3959 | B61: Chantiers C | C61: Administration | D61: Ouagadougou | E61: Centre | F61: +226 70 74 46 30 94 | H61: 2025-11-28 | I61: Standard | J61: 30 j | K61: 0
A62: 3969 | B62: SARL i | C62: Professionnel | D62: Ouagadougou | E62: Centre | F62: +226 72 19 86 21 16 | G62: contact3969@outlook.fr | H62: 2022-11-04 | I62: Argent | J62: Comptant | K62: 1500000
A63: 4004 | B63: Ets a | C63: Professionnel | D63: Koudougou | E63: Centre-Ouest | F63: +226 72 23 15 88 35 | H63: 2016-01-11 | I63: Standard | J63: 60 j | K63: 500000
A64: 4030 | B64: SARL n | C64: Administration | D64: Ouagadougou | E64: Centre | F64: +226 73 62 23 16 63 | G64: contact4030@gmail.com | H64: 2016-11-26 | I64: Standard | J64: Comptant | K64: 250000
A65: 4037 | B65: Menage 04037 | C65: Particulier | D65: Koudougou | E65: Centre-Ouest | F65: +226 71 30 93 87 90 | H65: 2025-03-05 | I65: Standard | J65: 30 j | K65: 0
A66: 4067 | B66: Menage 04067 | C66: Particulier | D66: Ouagadougou | E66: Centre | F66: +226 74 29 52 87 60 | H66: 2024-08-14 | I66: Standard | J66: 30 j | K66: 0
A67: 4171 | B67: Chantiers n | C67: Professionnel | D67: Ouagadougou | E67: Centre | F67: +226 78 17 44 71 51 | H67: 2022-06-13 | I67: Standard | J67: 60 j | K67: 250000
A68: 4245 | B68: SARL n | C68: Professionnel | D68: Ziniaré | E68: Plateau-Central | F68: +226 71 13 60 22 92 | G68: contact4245@entreprise.bf | H68: 2021-09-23 | I68: Argent | J68: 30 j | K68: 0
A69: 4253 | B69: SARL o | C69: Professionnel | D69: Kaya | E69: Centre-Nord | F69: +226 70 38 86 14 10 | G69: contact4253@entreprise.bf | H69: 2024-11-01 | I69: Or | J69: 30 j | K69: 0
A70: 4280 | B70: Menage 04280 | C70: Particulier | D70: Bobo-Dioulasso | E70: Hauts-Bassins | F70: +226 70 61 21 51 45 | H70: 2019-10-10 | I70: Standard | J70: Comptant | K70: 1500000
A71: 4285 | B71: Chantiers n | C71: Professionnel | D71: Bobo-Dioulasso | E71: Hauts-Bassins | F71: +226 78 86 44 51 60 | H71: 2019-08-06 | I71: Standard | J71: 30 j | K71: 0
A72: 4341 | B72: Chantiers r | C72: Entreprise | D72: Ziniaré | E72: Plateau-Central | F72: +226 71 89 53 94 60 | G72: contact4341@gmail.com | H72: 2019-03-29 | I72: Argent | J72: 60 j | K72: 5000000
A73: 4415 | B73: Ets n | C73: Professionnel | D73: Kaya | E73: Centre-Nord | F73: +226 79 39 32 99 32 | H73: 2025-03-08 | I73: Standard | J73: Comptant | K73: 0
A74: 4524 | B74: Chantiers t | C74: Entreprise | D74: Bobo-Dioulasso | E74: Hauts-Bassins | F74: +226 72 13 22 62 12 | G74: contact4524@yahoo.fr | H74: 2022-08-21 | I74: Standard | J74: 60 j | K74: 1500000
A75: 4653 | B75: SARL a | C75: Professionnel | D75: Bobo-Dioulasso | E75: Hauts-Bassins | F75: +226 75 29 26 61 79 | G75: contact4653@outlook.fr | H75: 2024-08-16 | I75: Standard | J75: 30 j | K75: 0
A76: 4654 | B76: Menage 04654 | C76: Particulier | D76: Ziniaré | E76: Plateau-Central | F76: +226 75 44 91 16 71 | H76: 2017-02-02 | I76: Standard | J76: Comptant | K76: 0
A77: 4660 | B77: Menage 04660 | C77: Particulier | D77: Ouagadougou | E77: Centre | F77: +226 72 32 81 61 50 | H77: 2025-01-05 | I77: Argent | J77: Comptant | K77: 0
A78: 4787 | B78: Menage 04787 | C78: Particulier | D78: Kaya | E78: Centre-Nord | F78: +226 73 33 14 43 55 | H78: 2025-12-10 | I78: Standard | J78: Comptant | K78: 0
A79: 4847 | B79: SARL u | C79: Professionnel | D79: Koudougou | E79: Centre-Ouest | F79: +226 72 40 36 48 84 | H79: 2025-05-27 | I79: Standard | J79: Comptant | K79: 0
A80: 4982 | B80: Menage 04982 | C80: Particulier | D80: Ouagadougou | E80: Centre | F80: +226 72 24 92 48 15 | H80: 2018-06-08 | I80: Standard | J80: 30 j | K80: 0
A81: 5037 | B81: Ets é | C81: Professionnel | D81: Ouagadougou | E81: Centre | F81: +226 79 29 81 51 49 | G81: contact5037@yahoo.fr | H81: 2021-10-23 | I81: Standard | J81: 60 j | K81: 500000
A82: 5046 | B82: Menage 05046 | C82: Particulier | D82: Ouagadougou | E82: Centre | F82: +226 76 39 80 98 82 | H82: 2022-10-09 | I82: Standard | J82: Comptant | K82: 1500000
A83: 5090 | B83: Menage 05090 | C83: Particulier | D83: Kaya | E83: Centre-Nord | F83: +226 75 33 63 62 21 | H83: 2023-10-15 | I83: Argent | J83: Comptant | K83: 0
A84: 5096 | B84: Menage 05096 | C84: Particulier | D84: Bobo-Dioulasso | E84: Hauts-Bassins | F84: +226 70 63 12 98 31 | H84: 2017-04-10 | I84: Standard | J84: Comptant | K84: 250000
A85: 5122 | B85: Menage 05122 | C85: Particulier | D85: Bobo-Dioulasso | E85: Hauts-Bassins | F85: +226 75 99 18 45 40 | H85: 2018-01-18 | I85: Argent | J85: 60 j | K85: 0
A86: 5173 | B86: Ets t | C86: Administration | D86: Ziniaré | E86: Plateau-Central | F86: +226 71 52 10 80 47 | H86: 2017-03-22 | I86: Standard | J86: 60 j | K86: 250000
A87: 5228 | B87: Ets a | C87: Professionnel | D87: Bobo-Dioulasso | E87: Hauts-Bassins | F87: +226 72 14 21 79 98 | G87: contact5228@yahoo.fr | H87: 2018-04-24 | I87: Or | J87: Comptant | K87: 1500000
A88: 5244 | B88: Ets o | C88: Professionnel | D88: Ziniaré | E88: Plateau-Central | F88: +226 78 65 91 68 13 | G88: contact5244@gmail.com | H88: 2017-01-14 | I88: Standard | J88: 30 j | K88: 0
A89: 5339 | B89: Menage 05339 | C89: Particulier | D89: Bobo-Dioulasso | E89: Hauts-Bassins | F89: +226 77 88 28 48 54 | H89: 2018-09-20 | I89: Argent | J89: 30 j | K89: 1500000
A90: 5345 | B90: Societe n | C90: Professionnel | D90: Ouagadougou | E90: Centre | F90: +226 71 40 82 37 68 | G90: contact5345@yahoo.fr | H90: 2026-04-04 | I90: Standard | J90: Comptant | K90: 0
A91: 5480 | B91: SARL o | C91: Professionnel | D91: Ouagadougou | E91: Centre | F91: +226 77 43 73 31 91 | G91: contact5480@entreprise.bf | H91: 2019-09-15 | I91: Standard | J91: Comptant | K91: 250000
A92: 5532 | B92: Chantiers m | C92: Professionnel | D92: Bobo-Dioulasso | E92: Hauts-Bassins | F92: +226 77 72 38 35 48 | H92: 2023-04-02 | I92: Standard | J92: 30 j | K92: 250000
A93: 5578 | B93: Menage 05578 | C93: Particulier | D93: Ziniaré | E93: Plateau-Central | F93: +226 76 44 70 84 38 | H93: 2024-10-31 | I93: Standard | J93: Comptant | K93: 250000
A94: 5725 | B94: Menage 05725 | C94: Particulier | D94: Ouagadougou | E94: Centre | F94: +226 76 66 75 33 58 | H94: 2019-10-30 | I94: Standard | J94: 30 j | K94: 0
A95: 5767 | B95: Menage 05767 | C95: Particulier | D95: Ouagadougou | E95: Centre | F95: +226 73 98 64 69 21 | H95: 2020-04-16 | I95: Standard | J95: 30 j | K95: 250000
A96: 5812 | B96: Menage 05812 | C96: Particulier | D96: Kaya | E96: Centre-Nord | F96: +226 76 56 64 72 60 | H96: 2021-06-02 | I96: Or | J96: 60 j | K96: 0
A97: 5882 | B97: Chantiers r | C97: Entreprise | D97: Bobo-Dioulasso | E97: Hauts-Bassins | F97: +226 79 90 89 72 40 | G97: contact5882@gmail.com | H97: 2021-02-10 | I97: Or | J97: 30 j | K97: 5000000
A98: 5892 | B98: Menage 05892 | C98: Particulier | D98: Ouagadougou | E98: Centre | F98: +226 75 28 48 96 43 | H98: 2016-10-19 | I98: Or | J98: Comptant | K98: 250000
A99: 5898 | B99: Menage 05898 | C99: Particulier | D99: Koudougou | E99: Centre-Ouest | F99: +226 76 76 39 62 50 | H99: 2024-11-14 | I99: Standard | J99: 30 j | K99: 1500000
A100: 5921 | B100: Menage 05921 | C100: Particulier | D100: Ouagadougou | E100: Centre | F100: +226 73 70 51 94 72 | H100: 2017-04-19 | I100: Standard | J100: 30 j | K100: 250000
...

Sheet magasins
A1: id_magasin | B1: nom | C1: ville | D1: quartier | E1: region | F1: type_magasin | G1: surface_m2 | H1: responsable | I1: ouverture
A2: 1 | B2: Sahel Distribution — Ouaga 2000 | C2: Ouagadougou | D2: Ouaga 2000 | E2: Centre | F2: Magasin | G2: 1450 | H2: A. Zongo | I2: 2016-03-01
A3: 2 | B3: Sahel Distribution — Gounghin | C3: Ouagadougou | D3: Gounghin | E3: Centre | F3: Magasin | G3: 900 | H3: F. Kaboré | I3: 2018-09-15
A4: 3 | B4: Sahel Distribution — Bobo Kibidwé | C4: Bobo-Dioulasso | D4: Kibidwé | E4: Hauts-Bassins | F4: Magasin | G4: 1100 | H4: S. Sanou | I4: 2017-06-01
A5: 4 | B5: Sahel Distribution — Koudougou Centre | C5: Koudougou | D5: Pole | E5: Centre-Ouest | F5: Magasin | G5: 650 | H5: R. Ouédraogo | I5: 2020-02-10
A6: 5 | B6: Sahel Distribution — Kaya Marché | C6: Kaya | D6: Marché | E6: Centre-Nord | F6: Magasin | G6: 520 | H6: I. Traoré | I6: 2021-11-05
A7: 6 | B7: Dépôt central — Zogona | C7: Ouagadougou | D7: Zogona | E7: Centre | F7: Dépôt | G7: 3200 | H7: M. Compaoré | I7: 2015-01-12

Sheet vendeurs
A1: id_vendeur | B1: nom_complet | C1: id_magasin | D1: date_embauche | E1: statut | F1: secteur_vente
A2: 1 | B2: Awa Zongo | C2: 2 | D2: 2019-08-11 | E2: Titulaire | F2: Comptoir
A3: 2 | B3: Issa Kaboré | C3: 3 | D3: 2018-07-03 | E3: Titulaire | F3: Comptoir
A4: 3 | B4: Fatoumata Sanou | C4: 4 | D4: 2022-06-21 | E4: Titulaire | F4: Comptoir
A5: 4 | B5: Boureima Ouédraogo | C5: 5 | D5: 2021-02-09 | E5: CDD | F5: Itinérant
A6: 5 | B6: Salif Traoré | C6: 1 | D6: 2017-07-04 | E6: Titulaire | F6: Itinérant
A7: 6 | B7: Mariam Compaoré | C7: 2 | D7: 2019-12-21 | E7: Titulaire | F7: Itinérant
A8: 7 | B8: Karim Sawadogo | C8: 3 | D8: 2020-05-31 | E8: Titulaire | F8: Itinérant
A9: 8 | B9: Rasmata Diallo | C9: 4 | D9: 2018-06-14 | E9: Titulaire | F9: Itinérant
A10: 9 | B10: Adama Bationo | C10: 5 | D10: 2016-07-28 | E10: Titulaire | F10: Itinérant
A11: 10 | B11: Safiatou Nikiéma | C11: 1 | D11: 2020-05-02 | E11: Titulaire | F11: Comptoir
A12: 11 | B12: Boukary Ouattara | C12: 2 | D12: 2019-05-20 | E12: Titulaire | F12: Comptoir
A13: 12 | B13: Alizéta Tapsoba | C13: 3 | D13: 2016-07-01 | E13: CDD | F13: Comptoir
... A23: 22 | B23: Nafissatou Zoungrana | C23: 3 | D23: 2018-12-13 | E23: CDD | F23: Itinérant

Sheet objectifs
A1: id_magasin | B1: annee | C1: mois | D1: annee_mois | E1: ca_objectif_ttc | F1: marge_objectif_pct
A2: 1 | B2: 2023 | C2: 1 | D2: 2023-01 | E2: 45600000 | F2: 0.195
A3: 1 | B3: 2023 | C3: 2 | D3: 2023-02 | E3: 48000000 | F3: 0.197
A4: 1 | B4: 2023 | C4: 3 | D4: 2023-03 | E4: 56640000 | F4: 0.201
A5: 1 | B5: 2023 | C5: 4 | D5: 2023-04 | E5: 54720000 | F5: 0.189
A6: 1 | B6: 2023 | C6: 5 | D6: 2023-05 | E6: 44160000 | F6: 0.187
A7: 1 | B7: 2023 | C7: 6 | D7: 2023-06 | E7: 37440000 | F7: 0.189
A8: 1 | B8: 2023 | C8: 7 | D8: 2023-07 | E8: 34560000 | F8: 0.196
A9: 1 | B9: 2023 | C9: 8 | D9: 2023-08 | E9: 38400000 | F9: 0.198
A10: 1 | B10: 2023 | C10: 9 | D10: 2023-09 | E10: 48960000 | F10: 0.192
A11: 1 | B11: 2023 | C11: 10 | D11: 2023-10 | E11: 58560000 | F11: 0.187
A12: 1 | B12: 2023 | C12: 11 | D12: 2023-11 | E12: 57600000 | F12: 0.198
A13: 1 | B13: 2023 | C13: 12 | D13: 2023-12 | E13: 55680000 | F13: 0.202
... A219: 5 | B219: 2026 | C219: 8 | D219: 2026-08 | E219: 14060000 | F219: 0.194

Sheet Calculs
A1: n° | B1: Fonction (telle que l'affiche Excel FR) | C1: Formule, telle qu'elle est stockée | D1: Valeur que la formule doit rendre | E1: Ce que la formule rend | F1: contrôle
A2: 1 | B2: NB sur la colonne des montants | C2: COUNT(ventes!M2:M481) | D2: 480 | E2: =COUNT(ventes!M2:M481) | F2: =IF(EXACT(D2,E2),"ok","à revoir") | G2: les 480 montants réellement numériques de la feuille nettoyée
A3: 2 | B3: NBVAL — compter tout ce qui est écrit | C3: COUNTA(ventes_brutes!A2:A490) | D3: 489 | E3: =COUNTA(ventes_brutes!A2:A490) | F3: =IF(EXACT(D3,E3),"ok","à revoir") | G3: les 489 lignes reçues, nombres et textes confondus
A4: 3 | B4: NB appliqué aux montants reçus | C4: COUNT(ventes_brutes!M2:M490) | D4: 0 | E4: =COUNT(ventes_brutes!M2:M490) | F4: =IF(EXACT(D4,E4),"ok","à revoir") | G4: le symptôme de l'import raté, dans le classeur : 0 montant numérique sur 489. Le CSV reçu en contient 3 (lignes 88, 179, 236), mais en collant la feuille dans un classeur ils redeviennent du texte — voyez C02 §5.1.
A5: 4 | B5: SOMME sur la feuille reçue | C5: SUM(ventes_brutes!M2:M490) | D5: 0 | E5: =SUM(ventes_brutes!M2:M490) | F5: =IF(EXACT(D5,E5),"ok","à revoir") | G5: le cas le plus dangereux du module : un total faux, zéro franc, et aucune erreur affichée. Le même =SOMME() sur le CSV importé avec conversion rend 2 444 FCFA — les 3 lignes saisies sans séparateur de milliers (lignes 88, 179, 236), et rien de plus.
A6: 5 | B6: SOMME | C6: SUM(ventes!M2:M481) | D6: 36073185 | E6: =SUM(ventes!M2:M481) | F6: =IF(EXACT(D6,E6),"ok","à revoir") | G6: le total de référence du module, sur la feuille nettoyée
A7: 6 | B7: MOYENNE | C7: AVERAGE(ventes!M2:M481) | D7: 75152 | E7: =AVERAGE(ventes!M2:M481) | F7: =IF(EXACT(D7,E7),"ok","à revoir") | G7: au niveau de la ligne, pas du ticket
A8: 7 | B8: MEDIANE | C8: MEDIAN(ventes!M2:M481) | D8: 37966 | E8: =MEDIAN(ventes!M2:M481) | F8: =IF(EXACT(D8,E8),"ok","à revoir") | G8: le centre robuste du module M02
A9: 8 | B9: ECARTYPE.STANDARD | C9: STDEV.S(ventes!M2:M481) | D9: 143915 | E9: =STDEV.S(ventes!M2:M481) | F9: =IF(EXACT(D9,E9),"ok","à revoir") | G9: dispersion sur échantillon
A10: 9 | B10: MAX | C10: MAX(ventes!M2:M481) | D10: 1229678 | E10: =MAX(ventes!M2:M481) | F10: =IF(EXACT(D10,E10),"ok","à revoir") | G10: et sa voisine MIN, qui est négative
A11: 10 | B11: MIN | C11: MIN(ventes!M2:M481) | D11: -150804 | E11: =MIN(ventes!M2:M481) | F11: =IF(EXACT(D11,E11),"ok","à revoir") | G11: un retour de marchandise, pas une saisie farfelue
A12: 11 | B12: QUARTILE.INC · premier | C12: QUARTILE.INC(ventes!M2:M481,1) | D12: 12950 | E12: =QUARTILE.INC(ventes!M2:M481,1) | F12: =IF(EXACT(D12,E12),"ok","à revoir") | G12: méthode inclusive, celle d'Excel 2010 et suivants
A13: 12 | B13: QUARTILE.INC · troisième | C13: QUARTILE.INC(ventes!M2:M481,3) | D13: 74234 | E13: =QUARTILE.INC(ventes!M2:M481,3) | F13: =IF(EXACT(D13,E13),"ok","à revoir") | G13: le IQR se lit dans la foulée
A14: 13 | B14: NB.SI sur la quantité reçue | C14: COUNTIF(ventes_brutes!I2:I490,">500") | D14: 7 | E14: =COUNTIF(ventes_brutes!I2:I490,">500") | F14: =IF(EXACT(D14,E14),"ok","à revoir") | G14: les sept quantités hors échelle du fichier reçu
A15: 14 | B15: SOMME.SI.ENS catégorie | C15: SUMIFS(ventes!M2:M481,ventes!H2:H481,"Plomberie") | D15: 8754982 | E15: =SUMIFS(ventes!M2:M481,ventes!H2:H481,"Plomberie") | F15: =IF(EXACT(D15,E15),"ok","à revoir") | G15: le CA d'un rayon, une condition
A16: 15 | B16: MOYENNE.SI.ENS | C16: AVERAGEIFS(ventes!M2:M481,ventes!H2:H481,"Electricité") | D16: 119088 | E16: =AVERAGEIFS(ventes!M2:M481,ventes!H2:H481,"Electricité") | F16: =IF(EXACT(D16,E16),"ok","à revoir") | G16: moyenne conditionnelle
A17: 16 | B17: NB.SI.ENS deux conditions | C17: COUNTIFS(ventes!H2:H481,"Peinture",ventes!K2:K481,">0") | D17: 8 | E17: =COUNTIFS(ventes!H2:H481,"Peinture",ventes!K2:K481,">0") | F17: =IF(EXACT(D17,E17),"ok","à revoir") | G17: les lignes remisées du rayon Peinture
A18: 17 | B18: RECHERCHEV, le piège classique | C18: VLOOKUP(1229678,ventes!G2:J481,4,FALSE) | D18: #N/A | E18: =VLOOKUP(1229678,ventes!G2:J481,4,FALSE) | F18: =IF(EXACT(D18,E18),"ok","à revoir") | G18: la valeur cherchée n'est pas dans la PREMIÈRE colonne de la plage : c'est l'exercice 6.2
A19: 18 | B19: RECHERCHEX, le même voyage | C19: XLOOKUP(ventes!M356,ventes!M2:M481,ventes!G2:G481,"non trouvé") | D19: Lame de lambris 4 m — réf 2 | E19: =XLOOKUP(ventes!M356,ventes!M2:M481,ventes!G2:G481,"non trouvé") | F19: =IF(EXACT(D19,E19),"ok","à revoir") | G19: aucun numéro de colonne à compter, et un mot de secours en cas d'absence
A20: 19 | B20: INDEX / EQUIV, la voie compatible | C20: INDEX(ventes!G2:G481,MATCH(MAX(ventes!M2:M481),ventes!M2:M481,0)) | D20: Lame de lambris 4 m — réf 2 | E20: =INDEX(ventes!G2:G481,MATCH(MAX(ventes!M2:M481),ventes!M2:M481,0)) | F20: =IF(EXACT(D20,E20),"ok","à revoir") | G20: ce que vous écrivez en 2019 et sous LibreOffice
A21: 20 | B21: EQUIV · la position | C21: MATCH(MAX(ventes!M2:M481),ventes!M2:M481,0) | D21: 355 | E21: =MATCH(MAX(ventes!M2:M481),ventes!M2:M481,0) | F21: =IF(EXACT(D21,E21),"ok","à revoir") | G21: position dans la plage ; ajoutez 1 pour obtenir la ligne du classeur, et vérifiez : M356
A22: 21 | B22: Tester si la colonne est entièrement numérique | C22: IF(COUNT(ventes_brutes!M2:M490)=COUNTA(ventes_brutes!M2:M490),"tout est nombre","du texte s’est glissé") | D22: du texte s’est glissé | E22: =IF(COUNT(ventes_brutes!M2:M490)=COUNTA(ventes_brutes!M2:M490),"tout est nombre","du texte s’est glissé") | F22: =IF(EXACT(D22,E22),"ok","à revoir") | G22: NB = NBVAL est le test de conformité d'une colonne numérique ; à écrire une fois par fichier, pas une fois par question
A23: 22 | B23: Réparer une cellule | C23: VALUE(SUBSTITUTE(ventes_brutes!M2," ","")) | D23: 56658 | E23: =VALUE(SUBSTITUTE(ventes_brutes!M2," ","")) | F23: =IF(EXACT(D23,E23),"ok","à revoir") | G23: la première ligne du fichier reçu, redevenue un nombre
A24: 23 | B24: Joindre les valeurs distinctes | C24: TEXTJOIN(", ",TRUE,UNIQUE(ventes!H2:H481)) | D24: Matériaux, Consommables, Quincaillerie, Plomberie, Electricité, Peinture, Bois & panneaux | E24: =TEXTJOIN(", ",TRUE,UNIQUE(ventes!H2:H481)) | F24: =IF(EXACT(D24,E24),"ok","à revoir") | G24: les sept rayons en une cellule, dans l'ordre du fichier
A25: 24 | B25: JOURS OUVRES | C25: NETWORKDAYS(DATE(2025,1,1),DATE(2025,12,2)) | D25: 240 | E25: =NETWORKDAYS(DATE(2025,1,1),DATE(2025,12,2)) | F25: =IF(EXACT(D25,E25),"ok","à revoir") | G25: le dénominateur d'une moyenne journalière honnête
A26: 25 | B26: Amplitude réelle de l'extrait | C26: MAX(ventes!B2:B481)-DATE(2025,1,1) | D26: 335 | E26: =MAX(ventes!B2:B481)-DATE(2025,1,1) | F26: =IF(EXACT(D26,E26),"ok","à revoir") | G26: une soustraction de dates rend un nombre de jours ; c'est plus lisible que DATEDIF et cela marche partout
A27: 26 | B27: Attraper l'erreur | C27: IFERROR(1/0,"rien à afficher") | D27: rien à afficher | E27: =IFERROR(1/0,"rien à afficher") | F27: =IF(EXACT(D27,E27),"ok","à revoir") | G27: à n'utiliser que si vous savez quelle erreur vous cachez
A28: 27 | B28: Contrôle de cohérence du montant | C28: ROUND(SUM(ventes!N2:N481)-SUM(ventes!L2:L481),0) | D28: 4 | E28: =ROUND(SUM(ventes!N2:N481)-SUM(ventes!L2:L481),0) | F28: =IF(EXACT(D28,E28),"ok","à revoir") | G28: la colonne utilitaire N recalcule quantité × prix × (1 − remise) ; l'écart avec le montant enregistré doit se compter en francs, pas en milliers
A29: 28 | B29: Réalisation vs objectif, extrait | C29: SUM(ventes!M2:M481)/SUMIFS(objectifs!E2:E219,objectifs!A2:A219,5,objectifs!B2:B219,2025) | D29: 0.182 | E29: =SUM(ventes!M2:M481)/SUMIFS(objectifs!E2:E219,objectifs!A2:A219,5,objectifs!B2:B219,2025) | F29: =IF(EXACT(D29,E29),"ok","à revoir") | G29: 18,2 % : ce ratio compare un extrait de 4 jours par mois à une cible annuelle. Il ne dit rien de la performance

Sheet TCD
A1: categorie | B1: lignes | C1: CA (FCFA) | D1: moyenne par ligne | E1: part du CA | F1: lignes remisées
A2: Matériaux | B2: =COUNTIFS(ventes!H2:H481,$A2) | C2: =SUMIFS(ventes!M2:M481,ventes!H2:H481,$A2) | D2: =IFERROR(C2/B2,"") | E2: =IFERROR(C2/$C$9,"") | F2: =COUNTIFS(ventes!H2:H481,$A2,ventes!K2:K481,">0")
A3: Consommables | B3: =COUNTIFS(ventes!H2:H481,$A3) | C3: =SUMIFS(ventes!M2:M481,ventes!H2:H481,$A3) | D3: =IFERROR(C3/B3,"") | E3: =IFERROR(C3/$C$9,"") | F3: =COUNTIFS(ventes!H2:H481,$A3,ventes!K2:K481,">0")
A4: Quincaillerie | B4: =COUNTIFS(ventes!H2:H481,$A4) | C4: =SUMIFS(ventes!M2:M481,ventes!H2:H481,$A4) | D4: =IFERROR(C4/B4,"") | E4: =IFERROR(C4/$C$9,"") | F4: =COUNTIFS(ventes!H2:H481,$A4,ventes!K2:K481,">0")
A5: Plomberie | B5: =COUNTIFS(ventes!H2:H481,$A5) | C5: =SUMIFS(ventes!M2:M481,ventes!H2:H481,$A5) | D5: =IFERROR(C5/B5,"") | E5: =IFERROR(C5/$C$9,"") | F5: =COUNTIFS(ventes!H2:H481,$A5,ventes!K2:K481,">0")
A6: Electricité | B6: =COUNTIFS(ventes!H2:H481,$A6) | C6: =SUMIFS(ventes!M2:M481,ventes!H2:H481,$A6) | D6: =IFERROR(C6/B6,"") | E6: =IFERROR(C6/$C$9,"") | F6: =COUNTIFS(ventes!H2:H481,$A6,ventes!K2:K481,">0")
A7: Peinture | B7: =COUNTIFS(ventes!H2:H481,$A7) | C7: =SUMIFS(ventes!M2:M481,ventes!H2:H481,$A7) | D7: =IFERROR(C7/B7,"") | E7: =IFERROR(C7/$C$9,"") | F7: =COUNTIFS(ventes!H2:H481,$A7,ventes!K2:K481,">0")
A8: Bois & panneaux | B8: =COUNTIFS(ventes!H2:H481,$A8) | C8: =SUMIFS(ventes!M2:M481,ventes!H2:H481,$A8) | D8: =IFERROR(C8/B8,"") | E8: =IFERROR(C8/$C$9,"") | F8: =COUNTIFS(ventes!H2:H481,$A8,ventes!K2:K481,">0")
A9: Total | B9: =SUM(B2:B8) | C9: =SUM(C2:C8) | D9: =C9/B9 | E9: =SUM(E2:E8) | F9: =SUM(F2:F8)
A11: Le TOTAL de la ligne CA doit être exactement le total de la feuille : s'il diffère d'un centime, un filtre est resté actif quelque part.

Sheet Mensuel
A1: mois | B1: CA de l'extrait (FCFA) | C1: nb de lignes | D1: objectif magasin 5 | E1: CA / objectif | F1: jours ouvrés du mois
A2: 1 | B2: =SUMIFS(ventes!M2:M481,ventes!B2:B481,">="&DATE(2025,$A2,1),ventes!B2:B481,"<"&DATE(2025,$A2+1,1)) | C2: =COUNTIFS(ventes!B2:B481,">="&DATE(2025,$A2,1),ventes!B2:B481,"<"&DATE(2025,$A2+1,1)) | D2: =SUMIFS(objectifs!E2:E219,objectifs!A2:A219,5,objectifs!B2:B219,2025,objectifs!C2:C219,$A2) | E2: =IFERROR(B2/D2,"objectif absent") | F2: =NETWORKDAYS(DATE(2025,$A2,1),EOMONTH(DATE(2025,$A2,1),0))
A3: 2 | B3: =SUMIFS(ventes!M2:M481,ventes!B2:B481,">="&DATE(2025,$A3,1),ventes!B2:B481,"<"&DATE(2025,$A3+1,1)) | C3: =COUNTIFS(ventes!B2:B481,">="&DATE(2025,$A3,1),ventes!B2:B481,"<"&DATE(2025,$A3+1,1)) | D3: =SUMIFS(objectifs!E2:E219,objectifs!A2:A219,5,objectifs!B2:B219,2025,objectifs!C2:C219,$A3) | E3: =IFERROR(B3/D3,"objectif absent") | F3: =NETWORKDAYS(DATE(2025,$A3,1),EOMONTH(DATE(2025,$A3,1),0))
A4: 3 | B4: =SUMIFS(ventes!M2:M481,ventes!B2:B481,">="&DATE(2025,$A4,1),ventes!B2:B481,"<"&DATE(2025,$A4+1,1)) | C4: =COUNTIFS(ventes!B2:B481,">="&DATE(2025,$A4,1),ventes!B2:B481,"<"&DATE(2025,$A4+1,1)) | D4: =SUMIFS(objectifs!E2:E219,objectifs!A2:A219,5,objectifs!B2:B219,2025,objectifs!C2:C219,$A4) | E4: =IFERROR(B4/D4,"objectif absent") | F4: =NETWORKDAYS(DATE(2025,$A4,1),EOMONTH(DATE(2025,$A4,1),0))
A5: 4 | B5: =SUMIFS(ventes!M2:M481,ventes!B2:B481,">="&DATE(2025,$A5,1),ventes!B2:B481,"<"&DATE(2025,$A5+1,1)) | C5: =COUNTIFS(ventes!B2:B481,">="&DATE(2025,$A5,1),ventes!B2:B481,"<"&DATE(2025,$A5+1,1)) | D5: =SUMIFS(objectifs!E2:E219,objectifs!A2:A219,5,objectifs!B2:B219,2025,objectifs!C2:C219,$A5) | E5: =IFERROR(B5/D5,"objectif absent") | F5: =NETWORKDAYS(DATE(2025,$A5,1),EOMONTH(DATE(2025,$A5,1),0))
A6: 5 | B6: =SUMIFS(ventes!M2:M481,ventes!B2:B481,">="&DATE(2025,$A6,1),ventes!B2:B481,"<"&DATE(2025,$A6+1,1)) | C6: =COUNTIFS(ventes!B2:B481,">="&DATE(2025,$A6,1),ventes!B2:B481,"<"&DATE(2025,$A6+1,1)) | D6: =SUMIFS(objectifs!E2:E219,objectifs!A2:A219,5,objectifs!B2:B219,2025,objectifs!C2:C219,$A6) | E6: =IFERROR(B6/D6,"objectif absent") | F6: =NETWORKDAYS(DATE(2025,$A6,1),EOMONTH(DATE(2025,$A6,1),0))
A7: 6 | B7: =SUMIFS(ventes!M2:M481,ventes!B2:B481,">="&DATE(2025,$A7,1),ventes!B2:B481,"<"&DATE(2025,$A7+1,1)) | C7: =COUNTIFS(ventes!B2:B481,">="&DATE(2025,$A7,1),ventes!B2:B481,"<"&DATE(2025,$A7+1,1)) | D7: =SUMIFS(objectifs!E2:E219,objectifs!A2:A219,5,objectifs!B2:B219,2025,objectifs!C2:C219,$A7) | E7: =IFERROR(B7/D7,"objectif absent") | F7: =NETWORKDAYS(DATE(2025,$A7,1),EOMONTH(DATE(2025,$A7,1),0))
A8: 7 | B8: =SUMIFS(ventes!M2:M481,ventes!B2:B481,">="&DATE(2025,$A8,1),ventes!B2:B481,"<"&DATE(2025,$A8+1,1)) | C8: =COUNTIFS(ventes!B2:B481,">="&DATE(2025,$A8,1),ventes!B2:B481,"<"&DATE(2025,$A8+1,1)) | D8: =SUMIFS(objectifs!E2:E219,objectifs!A2:A219,5,objectifs!B2:B219,2025,objectifs!C2:C219,$A8) | E8: =IFERROR(B8/D8,"objectif absent") | F8: =NETWORKDAYS(DATE(2025,$A8,1),EOMONTH(DATE(2025,$A8,1),0))
A9: 8 | B9: =SUMIFS(ventes!M2:M481,ventes!B2:B481,">="&DATE(2025,$A9,1),ventes!B2:B481,"<"&DATE(2025,$A9+1,1)) | C9: =COUNTIFS(ventes!B2:B481,">="&DATE(2025,$A9,1),ventes!B2:B481,"<"&DATE(2025,$A9+1,1)) | D9: =SUMIFS(objectifs!E2:E219,objectifs!A2:A219,5,objectifs!B2:B219,2025,objectifs!C2:C219,$A9) | E9: =IFERROR(B9/D9,"objectif absent") | F9: =NETWORKDAYS(DATE(2025,$A9,1),EOMONTH(DATE(2025,$A9,1),0))
A10: 9 | B10: =SUMIFS(ventes!M2:M481,ventes!B2:B481,">="&DATE(2025,$A10,1),ventes!B2:B481,"<"&DATE(2025,$A10+1,1)) | C10: =COUNTIFS(ventes!B2:B481,">="&DATE(2025,$A10,1),ventes!B2:B481,"<"&DATE(2025,$A10+1,1)) | D10: =SUMIFS(objectifs!E2:E219,objectifs!A2:A219,5,objectifs!B2:B219,2025,objectifs!C2:C219,$A10) | E10: =IFERROR(B10/D10,"objectif absent") | F10: =NETWORKDAYS(DATE(2025,$A10,1),EOMONTH(DATE(2025,$A10,1),0))
A11: 10 | B11: =SUMIFS(ventes!M2:M481,ventes!B2:B481,">="&DATE(2025,$A11,1),ventes!B2:B481,"<"&DATE(2025,$A11+1,1)) | C11: =COUNTIFS(ventes!B2:B481,">="&DATE(2025,$A11,1),ventes!B2:B481,"<"&DATE(2025,$A11+1,1)) | D11: =SUMIFS(objectifs!E2:E219,objectifs!A2:A219,5,objectifs!B2:B219,2025,objectifs!C2:C219,$A11) | E11: =IFERROR(B11/D11,"objectif absent") | F11: =NETWORKDAYS(DATE(2025,$A11,1),EOMONTH(DATE(2025,$A11,1),0))
A12: 11 | B12: =SUMIFS(ventes!M2:M481,ventes!B2:B481,">="&DATE(2025,$A12,1),ventes!B2:B481,"<"&DATE(2025,$A12+1,1)) | C12: =COUNTIFS(ventes!B2:B481,">="&DATE(2025,$A12,1),ventes!B2:B481,"<"&DATE(2025,$A12+1,1)) | D12: =SUMIFS(objectifs!E2:E219,objectifs!A2:A219,5,objectifs!B2:B219,2025,objectifs!C2:C219,$A12) | E12: =IFERROR(B12/D12,"objectif absent") | F12: =NETWORKDAYS(DATE(2025,$A12,1),EOMONTH(DATE(2025,$A12,1),0))
A13: 12 | B13: =SUMIFS(ventes!M2:M481,ventes!B2:B481,">="&DATE(2025,$A13,1),ventes!B2:B481,"<"&DATE(2025,$A13+1,1)) | C13: =COUNTIFS(ventes!B2:B481,">="&DATE(2025,$A13,1),ventes!B2:B481,"<"&DATE(2025,$A13+1,1)) | D13: =SUMIFS(objectifs!E2:E219,objectifs!A2:A219,5,objectifs!B2:B219,2025,objectifs!C2:C219,$A13) | E13: =IFERROR(B13/D13,"objectif absent") | F13: =NETWORKDAYS(DATE(2025,$A13,1),EOMONTH(DATE(2025,$A13,1),0))
A15: Total | B15: =SUM(B2:B13) | C15: =SUM(C2:C13) | D15: =SUM(D2:D13) | E15: =IFERROR(B15/D15,"")
A17: Lecture honnête du ratio CA / objectif : ici l'extrait ne couvre que les jours 1 à 4 de chaque mois (voir M02.C07), donc ce ratio ne mesure PAS la performance annuelle du magasin. Il mesure un extrait. La population entière donne un rapport de 1.62 à 3.27 selon le magasin-mois (le projet M03.P le discutera avec le fichier complet) : avant de parler de surperformance, on vérifie l'échelle du fichier d'objectifs.
